[
  {
    "Item": [
      "红枣黑米糕",
      "招牌牛肉面",
      "香辣牛肉包",
      "豆沙粽",
      "三鲜烧麦",
      "蛋黄鲜肉粽",
      "筒子骨粉",
      "豌豆炸酱粉",
      "港式豆沙包",
      "手工招牌牛肉灌汤包"
    ],
    "Name": "桃园灌汤包(创业店)",
    "Price": 4,
    "Description": null,
    "Address": "现代城华庭6栋一楼",
    "lat": 22.522833300989127,
    "lng": 113.93114349720871,
    "Comments": null,
    "CommentCount": 0
  },
  {
    "Item": [
      "香辣牛肉包",
      "豆沙粽",
      "三鲜烧麦",
      "香菇青菜包",
      "蛋黄鲜肉粽",
      "猪肉包子",
      "牛肉生煎",
      "招牌牛肉包",
      "奶黄包",
      "手工现做秘制红豆包"
    ],
    "Name": "桃园灌汤包(人民南路店)",
    "Price": 5,
    "Description": null,
    "Address": "人民南路海丰苑首层",
    "lat": 22.552410740828037,
    "lng": 114.13644538246052,
    "Comments": [
      "新出的红糖馒头真的很讨厌，经常吃出沙，你们家用的红糖都是红砖吗？！！从喜欢到忍受到讨厌，买十次吃七次沙块，是不是我每一次都把吃到沙的给吐出来你们会赔我修牙钱？！",
      "好吃，干净，价钱合适，吃了几年了，种类也多，望继续升级改进",
      "生怕这个店在这个位置不开了，这附近的小吃店本来就不多。希望一直开下去",
      "看起来环境不错，吃了一个味道绝对杠杠的，值得再来",
      "还不几几年的你的角度看携家带口斯帕克时间的没上扣扣瞌睡来了思考思考看到了",
      "r味道不错，买了五块钱三个包子。",
      "位置挺好，品种挺多，但是感觉包子略小，性价比有待提高。",
      "小笼包不错，挺精致的，要一块五一个，味道比较一般",
      "还不错。包子比之前小了一丢丢。一点油哈",
      "好吃好吃好吃，来武汉开分店就好了",
      "很赞哈，依然有折扣，是一个好店",
      "包子皮薄，肉鲜嫩，味道鲜美",
      "味道挺好的，早餐必选",
      "从开张就来了吃了，灌汤包一直保持水准，就是贵了差不多一倍了",
      "不错很好吃得包子！",
      "经济实惠骗子性价比高，味道还可以，包子有点小吃不饱。",
      "包子有点小，但是味道OK，只不过老板给我拿错了包子。",
      "挺好吃的，就是每天都要七八快     今天差一点就吃不到了    好险掉了一半",
      "基本上一个月有十五天晚上都吃这个，不说有多么好吃，就两个字实在",
      "青菜不熟，红糖包有沙",
      "这“桃园灌汤包”，有猪肉馅也有牛肉馅的，我们吃的是猪肉馅的，一口咬下，有小小的汤汁，一小撮肉馅，咸淡适中，味道新鲜可口。"
    ],
    "CommentCount": 21
  },
  {
    "Item": [
      "招牌鲜肉包",
      "清火绿豆沙",
      "酸菜粉丝包",
      "飘香野菜包",
      "红糖燕麦馒头",
      "招牌牛肉包",
      "时令青菜包",
      "黑米粥",
      "手工招牌牛肉灌汤包",
      "手工现做蛋黄流沙包"
    ],
    "Name": "桃园灌汤包(下沙店)",
    "Price": 7,
    "Description": null,
    "Address": "滨河路花好园1楼",
    "lat": 22.53402954639263,
    "lng": 114.07233495404891,
    "Comments": [
      "桃园灌汤包味道好，质量一直不错，大人和孩子都喜欢吃，喜欢吃猪肉包和牛肉包，棒！",
      "啊啊啊啊啊啊吧啊啊啊啊啊啊吧啊啊啊啊啊啊吧啊啊啊啊啊啊啊啊",
      "地方太小，不过包子好吃，豆浆也好喝，经常买。",
      "包子大小与小笼包差不多大，5元4个，味道不错",
      "一如既往的好。每当不知道吃什么的时候就选他们家！嘿嘿嘿",
      "味道很满意，服务需要加油，换了几批人了，还是拽拽的…",
      "方便快捷，好吃方便快捷，好吃方便快捷，好吃",
      "下沙店消费，好划算，四个包子送一瓶柠檬茶，草鸡开心，服务员态度很好哦，包子我还是认桃源的，希望下次能多多做活动",
      "很好吃很好吃个娘家宿舍你饿了呀老K破手咯婆老他我I所以是我是",
      "哈哈哈哈哈哈哈哈哈哈哈哈哈哈哈哈哈哈哈哈哈哈哈哈哈哈哈哈哈哈",
      "口味还好，汤太多，所以肉少，不过价钱还可以5块钱4个包！",
      "感覺也就一般般，沒什麼特別。價錢比別的地方要貴一點點。",
      "支付宝买单两个包子加一块送饮料，太划算了，好吃又实惠",
      "好的很！！！！！！好的很！！！！！！！！！",
      "好好好好好好好好好好好好好好好好好好好好",
      "在下沙学院下了课就近去吃的，觉得一般",
      "流沙包好吃，但是好贵啊，而且好小个",
      "包子超好吃，就是店员不鸟人",
      "流沙包很不错，其他就呵呵了",
      "非常好吃，我很喜欢的早餐",
      "还行吧，这东西怎么说呢",
      "还行。就是东西太小……",
      "很好吃，味道很不错",
      "点的外卖…包子太小",
      "好吃，味道不错哟。",
      "第一见识到的流沙包",
      "还不错，挺好吃的",
      "好包，喜欢，点赞",
      "经济实惠好吃不贵",
      "包子味道好点了这个冷饮，不新鲜，肚子不舒服",
      "每天都得排队买单，就是为了吃桃园灌汤包！",
      "包子好吃。很香，喜欢，推荐给大家。",
      "包子很香味道不错，很喜欢，推荐",
      "好味道，排队太多人",
      "还不错，就是那塑料杯包装的粥类能保质几个月那么久吗？",
      "包子有點小，不過流沙包和饅頭不錯",
      "好，就是有点贵，东西太小",
      "还行，就是东西太小",
      "这家的肉包子好吃又实惠, 包子一个一元,馅很扎实饱满,口感相当好。"
    ],
    "CommentCount": 39
  },
  {
    "Item": [
      "脆脆花生豆",
      "老字号八哥酸辣粉",
      "武汉热干面",
      "绿豆沙",
      "花生牛奶",
      "冰糖雪梨",
      "阿萨姆奶茶",
      "果粒橙",
      "怡宝",
      "雪碧"
    ],
    "Name": "老字号八哥酸辣粉湖南牛肉粉(大鹏店)",
    "Price": 10,
    "Description": null,
    "Address": "大鹏街道迎宾路52号滨海阳光园一楼商铺104号",
    "lat": 22.601171387512206,
    "lng": 114.48272769372392,
    "Comments": [
      "味道一般般，这里吃挺热的。呃~可以接受吧。整个粉有点斋，什么东西，像是酱油拌面吧。",
      "每次过来总要来分热个面配牛丸，感觉面还是比较正宗",
      "不错。挺好吃的。昨天买过一回。今天再来吃一次",
      "很好吃。麻辣够味道。还会再来的。这是我的成果。",
      "非常适合我的味道",
      "真的不是一般的差，我要热干面他放炸酱后来又放热干面的酱.",
      "同事推荐  还可以",
      "好像是新开的，环境不错，四周都是镜子，亮亮堂堂的",
      "吃过很多吃，很不错，喜欢吃他家的牛杂粉",
      "一般般，真的一般般，不是很推荐。店很小",
      "老板人很好，店里环境干净。",
      "好吃，环境好，店长也热情",
      "环境不错，卫生，好吃，我都很喜欢吃辣的，有喜欢吃辣的，还是不错哟",
      "很不错，来很多次了",
      "好好吃的，非常满意",
      "好好吃的，非常满意，下次带朋友过来",
      "店家很好，很nice",
      "很不错   经济实惠  …………………………………………",
      "味道挺好，不错。。。",
      "超好吃，下次再来。",
      "味道一般般，这里吃挺热的。呃~可以接受吧。整个粉有点斋，什么东西，像是酱油拌面吧。",
      "每次过来总要来分热个面配牛丸，感觉面还是比较正宗",
      "不错。挺好吃的。昨天买过一回。今天再来吃一次",
      "很好吃。麻辣够味道。还会再来的。这是我的成果。",
      "非常适合我的味道",
      "真的不是一般的差，我要热干面他放炸酱后来又放热干面的酱.",
      "同事推荐  还可以",
      "好像是新开的，环境不错，四周都是镜子，亮亮堂堂的",
      "吃过很多吃，很不错，喜欢吃他家的牛杂粉",
      "一般般，真的一般般，不是很推荐。店很小",
      "老板人很好，店里环境干净。",
      "好吃，环境好，店长也热情",
      "环境不错，卫生，好吃，我都很喜欢吃辣的，有喜欢吃辣的，还是不错哟",
      "很不错，来很多次了",
      "好好吃的，非常满意",
      "好好吃的，非常满意，下次带朋友过来",
      "店家很好，很nice",
      "很不错   经济实惠  …………………………………………",
      "味道挺好，不错。。。",
      "超好吃，下次再来。",
      "这边是以潮汕特色的肠粉为主，虽然口感鲜嫩清淡，但是还是挺有味道的。要了一碗牛肉粗粉加虎皮鸡蛋，坐下慢慢吃，鲜辣爽口，米粉也有嚼劲，牛肉大块很入味。",
      "这边是以潮汕特色的肠粉为主，虽然口感鲜嫩清淡，但是还是挺有味道的。要了一碗牛肉粗粉加虎皮鸡蛋，坐下慢慢吃，鲜辣爽口，米粉也有嚼劲，牛肉大块很入味。"
    ],
    "CommentCount": 42
  },
  {
    "Item": [
      "扯面",
      "麻什",
      "西安冰峰",
      "豆奶",
      "刀削面",
      "臊子面",
      "可乐",
      "凉皮",
      "油泼面",
      "红油抄手"
    ],
    "Name": "汉中小吃(盐田夜市街店)",
    "Price": 10,
    "Description": null,
    "Address": "盐田夜市街158-2号铺",
    "lat": 22.58809313640398,
    "lng": 113.86618368949699,
    "Comments": [
      "卫生环境很好，有陕西的味道，值得下次再来买哦，朋友们也可以多多光顾的",
      "味道非常好，特别适合陕西人的口味下次还会来吃",
      "好好好好好好好好好好好好好好好好好好好好好好",
      "很好吃，家乡的味道，汉中小吃是你不错的选择",
      "很喜欢这家的土豆丝，还有各种面食，附近住了快2年，这家绝对在附近的味道和环境是排的上号了，老板娘人非常热情",
      "老板人很好，做的饭很好吃",
      "味道挺好，量也足！",
      "老板服务态度很好",
      "油泼面味道就是美，下次还去这家汉中小吃店",
      "面很好吃，还不错每个星期天都有去吃。",
      "很好吃，卫生很好，老板老板娘很热心",
      "味道很好，特别是汤面，味道不错",
      "很好！物美价廉！",
      "点了肉夹馍，难吃的要命，朋友点的油泼扯面有头发←_←",
      "经常来吃，，但是唯独喜欢油泼面类，很不错",
      "好吃，来了两次了，下次还带朋友来，哈哈！",
      "经常吃的一家店，味道很正宗，推荐大家光顾",
      "我经常来吃.小店还可以.味道不错.",
      "味道很好，很不错。",
      "这家店已经成为了我每周必来吃的一餐，老板人很好。。。。。",
      "好吃，经常来吃，老板人很厚道。",
      "好吃实惠，建议大家都来尝尝！",
      "口味不错，服务到位，环境不错，价格合理"
    ],
    "CommentCount": 23
  },
  {
    "Item": [
      "猪杂汤河粉",
      "猪杂汤面",
      "瘦肉汤面",
      "鸡蛋牛肉肠",
      "枸杞叶猪杂汤",
      "炒牛肉河粉",
      "三及第汤饭",
      "瘦肉枸杞叶汤",
      "双蛋肉肠",
      "豆浆"
    ],
    "Name": "云辉肠粉王",
    "Price": 10,
    "Description": null,
    "Address": "白石洲1街15号",
    "lat": 22.53998120747779,
    "lng": 113.9741465497543,
    "Comments": [
      "份量还挺多的，环境比较差，口味比较咸，一般般。",
      "路过的看着不错就进来整两份，便宜好吃，快！",
      "味道很不错，加了肉，很好吃",
      "还不错还不错还不错还不错",
      "每天早上都在吃，味道还算不错的，比起其他的店都要好一点。",
      "味道不错，服务态度很热情，，，肠粉很劲道，，每天早上都吃",
      "还行，每天需要排队 还行，每天需要排队等待",
      "每天都会来这家，感觉他们家的肠粉棒棒的",
      "味道不错，最主要的是实惠，服务态度不错啊，好评！",
      "口感鲜嫩顺滑，味儿也不错，环境一般，推荐4颗星",
      "环境很清洁，速度也很快。蛋肠4元/份",
      "美团外卖上太贵了，而且还要配送费",
      "吃肠粉都是来这家吃。很好吃",
      "味道不错哦，值得推荐",
      "没地方吃:随便吃点",
      "味道挺正宗的，吃过很多家了，特别是那个辣椒酱相当棒！作为湖南人大爱。",
      "味道不错，香嫩细滑，环境干净简单。"
    ],
    "CommentCount": 17
  },
  {
    "Item": [
      "肥肠米粉",
      "青椒回锅肉",
      "红烧肥肠饭",
      "凉拌豆干",
      "酸辣猪肝面",
      "麻辣卤鸭脚",
      "凉拌牛肉",
      "凉皮",
      "杂酱面",
      "蛋炒饭"
    ],
    "Name": "渝忠面馆",
    "Price": 10,
    "Description": null,
    "Address": "迎宾路与鹏新东路交叉口东100米",
    "lat": 22.709316339021342,
    "lng": 114.24657009218116,
    "Comments": [
      "食材新鲜，口味独特，值得品尝？",
      "面馆很好，价格公道，环境优美。我们曾经没有手机，没有电脑，没有wifi，那时候的我们，过的比现在开心。 ​​​ ​​​​",
      "好吃的不得了！欢迎大家来品尝！",
      "老罗推荐的。。。吃饱了。。。好辣。。非常四川",
      "还可以吧，开业到现在，天天吃",
      "很好吃 正中重庆口味 麻辣味",
      "四川口味，都不错",
      "店面干净，整洁，环境雅静，面馆面地方风味浓郁，非常好",
      "面条不错，口感很好。",
      "味道超好 每周都吃",
      "味道不错欢迎大家来品尝！多提宝贵意见",
      "面馆味道不错，有川味的韵味，继续加油！",
      "很多种面，调料也不错，面也劲道，口味不错，值得品尝"
    ],
    "CommentCount": 13
  },
  {
    "Item": [
      "肠粉",
      "原味豆浆",
      "瘦肉河粉",
      "蒸米粉",
      "枸杞瘦肉汤",
      "烧骨芥菜粥",
      "猪杂河粉",
      "叉烧蛋肠",
      "瘦肉蛋肠",
      "生菜"
    ],
    "Name": "威记肠粉王(蛇口店)",
    "Price": 10,
    "Description": null,
    "Address": "花果路32-5号",
    "lat": 22.495532852907246,
    "lng": 113.93481507753873,
    "Comments": [
      "【环境】小店环境，绝对不能要求太高。 【服务】真心有些人手不够，不过对于这种价格不高小店是能理解的。 【口味】深圳连锁肠粉店，味道很好吃。",
      "早餐经常去吃肠粉，味道还行吧！",
      "威记做的越来越好啦，开了好几家连锁店，味道很不错哦，早上一家人去吃，大人小孩子都很满意，鸡蛋肠粉，鲜肉肠粉，最爱吃的就是这两个",
      "好吃，份量足，第二次吃了。豆浆也好喝。",
      "好吃，好好吃!不妨来尝尝!!!",
      "味道还行，习惯性好评。比上次那家要差一点点。",
      "味道还可以。就是汤汁 比较少。 不错不错不错。",
      "味道很好，老板很热情，值得再次来吃，回购！",
      "味道很好，到广东就得吃肠粉，好吃管饱",
      "环境很好，量很足，吃他们家很安心",
      "味道非常棒，特别是瘦肉面！",
      "肉多便宜，大家都可以试试",
      "味道很棒，干净卫生！",
      "味道不错，挺好吃的",
      "位置很好找，肠粉，汤粉都好吃，味道不错。干净美味，经常来。",
      "味道很鲜美，好吃",
      "不是我想要的味道",
      "很不错，非常好吃，店内卫生干净，非常不错！",
      "分量足，味道真的很不错！！！",
      "吃过一次，一般般吧，开了有一段时间了",
      "味道好，不错，就是离我住宿远了点!",
      "肠粉算得上是广东这边的特色，好吃不贵"
    ],
    "CommentCount": 22
  },
  {
    "Item": [
      "玉米粥",
      "蒸南瓜",
      "素菜包",
      "例汤",
      "炸土豆块",
      "红薯丸",
      "小米粥",
      "豆浆",
      "红烧茄子",
      "炒面"
    ],
    "Name": "净行天厨(莲塘总店)",
    "Price": 10,
    "Description": null,
    "Address": "聚宝路聚宝商业中心二楼",
    "lat": 22.567823521231198,
    "lng": 114.17622738094005,
    "Comments": [
      "【环境】虽然不是奢华的装修，简单的让人舒服。非常素雅。 【服务】每个人都很安静，舒适。 【口味】没有肉，偏清淡，做的挺好吃。价格非常合理。",
      "【口味】很好 【服务】热情周到细致",
      "干净清单，合胃口素食，我精彩来吃，但不可以拍照，慈悲为怀，感恩",
      "经常来这里吃素食，样式还比较多的，总的来说满意吧。",
      "味道不错.坐的位置太少.希望能多点.地方有点小！",
      "还是老味道、还是那么好吃、还是喜欢来这里吃！",
      "便宜 干净 整洁 还算美味，挺不错的",
      "去吃过几次，味道不错，菜色也可以，价格合适不贵！提倡吃素！",
      "还可以吧，比较喜欢以前有的艾板，可惜很久没有了，还会来的",
      "支付寶盡然有紅包減免好耶下午嘚菜肴蠻不錯嘚喲好評噶",
      "人很多，素菜种类还是挺多的，味道也不错。",
      "非常感谢感谢您非常喜欢非常满意",
      "味道可以，价格也便宜哦",
      "下午有五塊紅包抵扣誒thats much of bravo",
      "好評習慣性好評好吧就這樣囖今天來嘚稍微晚了點",
      "味道还行.位置不多.地方有点小.希望改进哦！",
      "滿分好評不解釋多餘嘚就這樣還湊夠最後幾個字",
      "又可以刷支付寶興奮噶，掌櫃嘚以後繼續用支付寶啊 每單也才扣幾分錢嘛大不了俺多刷五毛囖",
      "習慣性好評好吧就這樣囖湊夠字數俺就閃人囖",
      "味道很不错，菜式很多物良价美，值得推荐！",
      "難道以後又不能用支付寶了乜？不要這樣噶",
      "習慣性好評就這樣囖有時間都會來這裡噶",
      "菜式新鲜，美味，品种类众多，人流量超多，超赞的一个自助素食店!",
      "不错，高峰人很多！",
      "習慣性好評就這樣囖這裡終於可以用支付寶囖以後會常來的囖",
      "家常素菜馆，卫生，味道还行，物美价廉，值得拥有。",
      "10元的自助餐素食，菜式多味道都不错，经常来光顾",
      "超级无敌良心的店，又便宜又好吃，还干净100分",
      "菜式多，美味，10块钱自助餐，便宜",
      "盡然有紅包折扣俺可係付款了10.24噶",
      "炒的菜还是可以的，这一家的米饭挺香，很喜欢。",
      "人太多，有点拥挤。没有头两年的口味好",
      "红薯丸，这个很好吃，虽然是炸的，但是一点也不过于油腻。玉米粥，简简单单的一碗粥，很浓的玉米味，好像加了小苏打，喝下去很暖胃。蒸南瓜，简单的做法，味道很赞。自助餐菜式还是蛮多的，性价比高。"
    ],
    "CommentCount": 33
  },
  {
    "Item": [
      "泡椒鸡杂",
      "攸县香干",
      "黄金豆腐",
      "酸辣鹅肠",
      "干锅茶树菇",
      "金银馒头",
      "梅菜扣肉",
      "紫菜蛋汤",
      "农家小炒肉",
      "米饭菜不包括米饭"
    ],
    "Name": "豪湘楼",
    "Price": 10,
    "Description": null,
    "Address": "公明街道上村长春路99号",
    "lat": 22.791866434827593,
    "lng": 113.90083673541471,
    "Comments": null,
    "CommentCount": 0
  },
  {
    "Item": [
      "番茄沙司",
      "维他柠檬茶",
      "吞拿鱼紫菜包饭",
      "鱿鱼丝饭团",
      "丘比千岛酱",
      "辣酱酱",
      "培根咸蛋黄泡菜紫菜包饭",
      "八爪鱼芝士肉松紫菜包饭",
      "鱼子酱",
      "鳗鱼咸蛋黄手卷"
    ],
    "Name": "韩式紫菜包饭",
    "Price": 11,
    "Description": null,
    "Address": "粤海街道南海大道3688深圳大学芸香阁一楼雨巷超市102专柜",
    "lat": 22.53310743162975,
    "lng": 113.93889228053521,
    "Comments": [
      "手抖哈哈哈，好吃八爪鱼加沙拉最爱好吃八爪鱼加沙拉最爱",
      "好久没吃了，念了好久终于又买了一次，但是感觉没以前好吃了",
      "还可以，偶尔没食欲的时候会吃。就是比较贵",
      "非常好吃，每次都去买泡菜味的紫菜包饭……",
      "好吃好吃好吃好吃好吃好吃好吃好吃够字了吗",
      "味道还不错，就是感觉分量偏少",
      "很不错，经常来买",
      "很好吃，價格合理",
      "这家的紫菜包饭非常好，也新鲜。",
      "服务不错，可以微信或者支付宝支付。可以点紫菜包饭或者是饭团，饭团6块起价，包饭是十几块。没有座位的，基本都是拿回宿舍吃的学生"
    ],
    "CommentCount": 10
  },
  {
    "Item": [
      "重庆酸辣粉",
      "葡萄双皮奶",
      "青菜瘦肉粥",
      "蜜豆豆花",
      "葡萄豆花",
      "荆典牛杂面",
      "荆典肥肠面",
      "西米露豆花",
      "荆氏招牌双皮奶",
      "蒸饺"
    ],
    "Name": "荆品豆花(新安店)",
    "Price": 11,
    "Description": null,
    "Address": "新安街道翻身路322号",
    "lat": 22.56569759414743,
    "lng": 113.90252435412829,
    "Comments": [
      "这家荆品豆花在住处附近，偶尔吃腻了米饭会过来换一换口味，吃点面或者粉吃。有些候再来碗双皮奶或者豆花，适合夏天吃。这次和儿子两人各点不同的粉，还有不同口味的豆花，一人一份，味道还可以。",
      "好吃，吃了好多次了，不过第一次评论，不论饺子还是酱面味道都很不错好吃，甜点也不错",
      "店里环境还不错。不知道味道怎么样先~评论说要20字，这句话打上去估计就有20字了",
      "好吃第二次过来了，原来这边也有双皮奶",
      "豆花味道真不错，热干面味道稍微有点咸，不过点了中辣的，感觉很不一样",
      "木瓜牛奶浴   小吃拼盘    炸酱面",
      "他们家的热干面，豆腐花味道很赞，下班经常过来吃。",
      "饺子非常好吃，不错。。。。。。。。。。。。。。",
      "挺好的，棒棒哒，，，，，，，，，，想，吃，，",
      "煎饺真的好吃，最爱他家的煎饺了，豆花也不错。",
      "走好远来吃的，挺不错的。如果不远肯定经常吃",
      "感觉不错，环境挺好，隔壁正放着南合文斗的《化作满天相思的雨》，勾起了大学生活的想念",
      "味道很不错的。环境很好，就餐的人也很多。",
      "双皮奶和豆花真是店里的特色招牌，小吃，和面都很不错，恰好是我喜欢的style~",
      "环境，服务和菜品都不错，关键是就在家门口楼下，很方便的，随时可以过来吃，赞一个",
      "除了豆花好吃，其他的真一般",
      "还好，之前来过一次，所以又过来光顾，豆腐花爽滑好吃，都过来尝尝看哦",
      "环境很不错，味道也不错",
      "还行，感觉绿豆沙还不错",
      "豆花不错，煎饺也好吃",
      "经常来，很好，服务态度也很好，哈哈哈哈哈哈哈哈哈哈哈哈哈哈哈",
      "还不错，藕尖好吃",
      "哈哈就好好斤斤计较叽叽叽叽叫姐姐斤斤计较斤斤计较",
      "环境不错，食物的分量也很大，一碗面我们两个人吃都足够了！虽然不喜欢吃辣，也觉得挺好吃的",
      "记录里快快乐乐咯怪我莫非你你你好吗红魔鬼鬼鬼一样hen'zruglegeimizhu",
      "服务很好 豆浆很好喝纯。    下次还来。酸藕不错呀",
      "棒棒哒，豆花很好吃，煎饺菲菜的最好吃，亲测",
      "还带凉品的，双皮奶不错哦，就是有点少啊，",
      "服务太慢了，我第一个来，最后一个才上面条，前面有五六个人都面条都做好了，还找借口",
      "木瓜牛奶浴，超级难吃，木瓜是生的，牛奶是奶精粉冲的，第一次去，也是最后一次",
      "这家店的豆腐花和面食都挺不错的",
      "我也不知道好不好吃。毕竟菜还没上。点评有奖励就点评一下把!",
      "味道不错，还会再来",
      "环境好，味道也好",
      "面条做的真的nice，老板娘人也很漂亮，吃饭是一种享受～",
      "味道和服务都是可以的，推荐杂酱面配豆浆，早餐量太足了！",
      "经常买豆花和双皮奶很好吃，甜点的拼盘个人不爱吃。",
      "小吃品类齐全，卫生干净，口味独特，老板热情好客",
      "分量很足，味道也好，整体环境更像是小清新的风格",
      "品种很多很喜欢玉米饺子在下班回家的路上，方便",
      "还不错，路过这家店就会进来要一份荆品豆花来",
      "经常去，再点了豆腐花小吃之类的，不错！",
      "正宗湖北味道，环境优雅，翻身地铁站B出口，交通方便，最主要是好吃，下次我还来",
      "第二次消费！好评！因为钱没带够，老板不要了，说下次在给，我付清就为写好评！",
      "不错，环境很好，也挺好喝",
      "没有厕所 服务态度也不行",
      "湖北荆州人正宗的荆品豆花，正宗热干面，牛肉面，老乡要多来尝尝哦",
      "态度很好，卫生很好吃",
      "呵呵呵呵呵→_→。第一次吃，还没上菜，还不清楚，，，，，，，",
      "这个店很好，经常来",
      "还是那个味道，好吃",
      "很好吃，值得常来，higjsjdhdusjdvfhfhfh",
      "三鲜面里面的鱼糕有家里的味道，好吃，下次还会来！",
      "好难啊，好难啊，好难啊，好难啊，好难啊，好难啊",
      "味道不错，口味很地道，环境不错，下次还来的哦",
      "总体味道很好，就是凉拌菜味道要稍稍改善一下",
      "环境干净，份量够多。来了几次了",
      "不错，环境挺好的；豆腐花很棒。",
      "味道一般，豆花不是很碎，",
      "环境很舒适，味道很不错！",
      "口味过得去，不过不会常去",
      "不咋地，哈哈，个人口味",
      "环境不错，口味也适中。",
      "味道很不错 常常过来吃",
      "很好吃了，挺有特色的",
      "炸酱面的味道不错，赞",
      "不错。满合胃口的。",
      "味道不错 吃了很多次",
      "服务好，口味好可以",
      "正宗湖北荆州口味！",
      "很棒，味道很好吃",
      "红红火火恍恍惚惚",
      "经常去了，不错，分店也多",
      "环境还行，价格稍微贵了点，豆花是甜点不是重庆那种豆花，尝尝鲜",
      "萝卜牛腩套餐里面的绿豆沙好正啊",
      "额服务态度好，口味好！！！超级好吃到升天！！！！",
      "豆腐花很滑很香，值得一试，粉的豆配菜很香口",
      "不好吃 量少且贵"
    ],
    "CommentCount": 78
  },
  {
    "Item": [
      "肠粉",
      "叉烧",
      "玉米肠",
      "辣椒酱",
      "牛肉肠",
      "鸡蛋肠",
      "配料",
      "猪肝肠",
      "肉饼肠",
      "腊肠火腿肠"
    ],
    "Name": "云髻山肠粉(红岭店)",
    "Price": 11,
    "Description": null,
    "Address": "红岭中路2029-2号",
    "lat": 22.557540144289902,
    "lng": 114.11073235651754,
    "Comments": [
      "吃了好多吃。肠粉鲜嫩柔滑。价格很便宜。店内服务人员有一个",
      "体面吃的，刚好就在楼底下，买起来也方便。他们都是自己用米磨得浆，好吃看的见",
      "第二次来吃肠粉，在红岭中路上。特别好吃，尤其是玉米肠粉。",
      "支付宝骗人呢说话你就可以解决了一个花了为什么说人的",
      "味道不错的，喜欢",
      "每天都吃这家的肠粉做早餐，百吃不厌，巴适得很哦",
      "六块的肠粉才花了六毛，明天还去买",
      "很香的辣椒哈哈哈",
      "东西好吃，但是店长的态度跟吃了狗屎一样",
      "经常来这里吃，味道确实不错。价钱合适，各种都有，肠粉很正宗呢，加点辣哼爽",
      "打包带走的，味道还不错！",
      "分量较少，味道还行",
      "很好！很好！很好！"
    ],
    "CommentCount": 13
  },
  {
    "Item": [
      "客家腌面",
      "蚝油生菜",
      "酿苦瓜",
      "枸杞三及第汤",
      "蚝油西兰花",
      "咸菜牛肉汤",
      "客家黄酒煮鸡蛋"
    ],
    "Name": "小5腌面(流塘店)",
    "Price": 11,
    "Description": null,
    "Address": "建安二路44号",
    "lat": 22.58483835619194,
    "lng": 113.89573328574635,
    "Comments": [
      "三及弟汤鲜味道还不错。。。。。",
      "腌面，五花肉！好吃！！五花肉本身就做得很好吃，老板娘还在不断改进，加了酸菜，例汤超级配！需要注意的是葱花的新鲜度就完美了！辣酱差点忘了，拇指！",
      "中午经常来这里吃，服务态度好，东西香，好吃啊啊啊啊啊啊啊啊啊啊，经常来吃。",
      "经常吃，那三及第汤是总都吃不腻，好赞，哈哈",
      "味道非常不错，家乡的味道，又干净卫生，人太多还排了半小时的队才能吃上，打五折超值了，同事们都说要去试试用",
      "吃了么那多家客家面，这家实惠味道好，卫生",
      "感觉很温馨，环境不错，价格实惠，下次还来",
      "一直支持，很好吃，很符合我的口味",
      "好久没吃老家的味道了，不错。正宗",
      "住着附近，解决周末吃饭的首选",
      "量太少了，就一点点，吃不饱",
      "熟悉的掩面味道，很正宗啦～",
      "服务不错，口味很适合。",
      "可以，值得推荐。",
      "很好吃，不能错过",
      "挺正宗的，有老家的味道，我个人还是比较喜欢吃的",
      "可以可以可以可以可以可以，哈哈哈哈哈哈哈",
      "这个阉面吧，我觉得不错，为什么呢？因为我想把评论加到20个字以上，所以必须有点废话来凑合",
      "两个小男生的店，一大早的不容易，勤劳就是美德。东西也不错",
      "老闆，要打掃衛生了，比最開始開業時候感覺髒了，亂了"
    ],
    "CommentCount": 20
  },
  {
    "Item": [
      "红油猪耳",
      "麻辣水煮鱼",
      "火锅面",
      "红薯粉",
      "绿茶饼",
      "鸭虾恋",
      "潮汕豆腐皮",
      "手工面",
      "麻辣牛肉",
      "鸭翅"
    ],
    "Name": "福德鸭鸭爪爪特色火锅",
    "Price": 11,
    "Description": null,
    "Address": "华南城环球物流中心2楼",
    "lat": 22.68208412966312,
    "lng": 114.13011349641442,
    "Comments": [
      "这种先吃干锅后加汤涮火锅的吃法吃得很爽",
      "很好吃，很好吃，很好吃很好吃，很好吃，很好吃很好吃，很好吃，很好吃",
      "不错啊！第一次，还是挺好味的很好嚼碎，很熟，服务也不错！环境干净卫生！",
      "一如继往，带孩子吃的不辣的，分量十足，还会光顾",
      "味道不错，我和朋友每个礼拜天都过来光顾！",
      "口味还不错，年前就吃过一次，店面重装了。环境更好，吃光光了。100个赞",
      "味道还算不错，可以来试试！！！！！！！！",
      "这是我吃火锅最差的一家，味道差，菜的分量少不说，还贵的很。。以后不会再去了。。",
      "环境、菜式都不错，服务态度很好，量很足，四个人吃的很饱，下次还会再来",
      "好喝，真材实料，非常好喝",
      "好好吃哦，下次还来",
      "服务热情推荐饮料好喝鸭爪爪味道可以 天热 也没有上火的感觉",
      "味道不错，来第二次了，服务态度也挺好的，好评",
      "还好吧嗯嗯嗯嗯嗯嗯好的谢谢谢谢@你是的事啊？？？费流量的是不知道你了？额好吧好吧你了",
      "二十字二十字二十字二十字二十字二十字二十字",
      "很好吃哦哦哦哦哦哦哦哦哦哦哦哦哦哦哦哦哦哦",
      "味道很好。店员服务很周到。666",
      "味道非常非常非常好，服务非常好！",
      "女朋友很喜欢吃这里的鸭爪",
      "味道好及了，服务也好",
      "很不错，好吃!推荐朋友们都来尝尝。四川重庆风味的特色火锅",
      "环境很不错，味道不错，分量很足",
      "环境不错，火锅也挺好吃！",
      "环境不错，味道也还不错",
      "肉挺多的 两个人吃撑了",
      "牛肉带骨头，我平生吃了那么多火锅。第一次",
      "真的挺好吃的。我都同事都很喜欢。",
      "味道不错，也不辣，"
    ],
    "CommentCount": 28
  },
  {
    "Item": [
      "捞面",
      "北京炸酱面",
      "酸豆角肉沫饭",
      "酸辣土豆丝饭",
      "红萝卜肉丝饭",
      "羊肉饺",
      "青瓜肉片饭",
      "青菜肉片饭",
      "大葱猪肉饺",
      "红萝卜玉米猪肉饺"
    ],
    "Name": "冀乡缘面馆",
    "Price": 12,
    "Description": null,
    "Address": "新湖路二郎田鸡北150米",
    "lat": 22.571984556365635,
    "lng": 113.8815441873055,
    "Comments": [
      "超级实惠，5个人点了8个菜一共花了不到200。",
      "喜欢吃面食的可以去尝尝，地道手工面，饺子也不错，物廉价美。",
      "味道好好，下次还来。如果能再淡一点就完美了！",
      "值得跑很远过来吃，面食很到位！天天吃不腻。",
      "北方面馆，北方的味道，北方的朋友可以来吃下，价格也挺便宜的，赞一个",
      "很不错！我经常去！",
      "老板人很好，和蔼可亲我天天晚上来这里吃饭，北方味道，加大蒜",
      "很好，家乡味我也是北方，天天来这里吃饭，正宗的饭，老板人也很好，都是老乡，也都认识我了，哈哈",
      "饺子不错，地道北方味，就在楼下，方便实惠，下次再来",
      "北方面食味道不错，而且价格也不贵，经常和公司的同事来吃，老板，人也挺好，经常给我们优惠。",
      "～～～～～！？？～。。不错，现做的。。。。。。",
      "吃过无数次了。最推荐的是青椒肉丝手工面。味道很好，而且分量超足。我一般都吃不完。",
      "不错不错，味道很好，以后会经常来。",
      "老板不错，空调给力点。",
      "很好～～很实在的一家店",
      "便宜好吃，份量多",
      "饺子自己包的，很好吃，10元一份，其它北方菜也不少",
      "和朋友做了两桌，每桌十多个菜一共才400多。赞",
      "经常去这里吃，口味不错，环境也可以。很舒适。",
      "北方的味道，北方人应该都很喜欢吧。",
      "分量足，味道好，老板一家服务也热情",
      "其他都可以，辣子鸡应该叫辣子鸡皮",
      "很棒，很良心的店",
      "味道不错，价格实惠，公司的每周都会来这家聚餐，大家很满意",
      "公司员工都喜欢在这里吃，都快成我们公司的食堂了，好吃不贵",
      "不错，非常好，还是原来的味道，交通也方便方便 ，很好找！",
      "饺子挺好吃的，价格实惠。就是没有驴肉火烧",
      "经常吃，吃了2年了，价格实惠，味道好",
      "比较有特色的面馆",
      "口感，味道都很好",
      "哈不错的一家面馆",
      "北方的味道，不错",
      "满意，烧鸡超好吃"
    ],
    "CommentCount": 33
  },
  {
    "Item": [
      "正宗牛筋丸汤",
      "葱花煎蛋饭",
      "枸杞汤",
      "腌米粉",
      "腐竹牛腩饭",
      "及弟汤",
      "苦瓜煎蛋饭",
      "红烧肉饭",
      "五香焖鸭汤",
      "卤香肉沬汤面"
    ],
    "Name": "客家张记腌面馆(兴围店)",
    "Price": 12,
    "Description": null,
    "Address": "兴围村兴华路3栋1号铺",
    "lat": 22.64041751454451,
    "lng": 113.84002801003952,
    "Comments": [
      "感觉还不错。好吃怎么样才能凑够20个字呢，好头疼！样品多样。够了吧，那么电影券记得给我啊，老板！谢谢了！我是支付宝的忠实用户啊！我要看太空旅客！",
      "豉汁排骨，香菇焖鸡都非常好吃，每周必吃的一家店，就是价格稍微有点贵",
      "好想够20个字，好辛苦好吃，速度快，快一点够20个字吧，好像够了",
      "不错的面馆，人气高，手艺好，味道不错，多来尝尝，以后要常来哦！",
      "环境很干净，味道比较清淡，典型的客家风味，喜欢的可以过来尝试",
      "一直都感觉不错以后还会再来，就是人多地方小不太方便",
      "非常好，第一次在这里吃，环境哈，服务也很好",
      "饭菜真难吃，菜少的要命，有tm贵。",
      "鸭翅很好吃(｢･ω･)｢嘿",
      "可以，不错，老顾客了",
      "饭的口味不是太好吃，",
      "饭阔以再做好点！！",
      "汤很好喝 粉有点硬",
      "环境挺好，味道符合南方人，经常在这里吃饭，价格合适",
      "店面干净卫生、饭菜味道好、ヽ(^Д^*)/.○✨",
      "20减4真的好爽啊！这家店一直都很卫生干净",
      "哦敬酒你牛名额你听oil灵敏提就孤零零你就",
      "很好、支付宝支付便宜又实惠而且又方便",
      "论罪拔魔KKK来咯某件KKK",
      "非常好啊，离家近啊……大喊大叫短裤想把那些明星面膜，大家都觉得苦。",
      "已经忘了这家店的存在…",
      "真的很不错喔，值得推荐，伙伴们可不要错过哟～～～～～～～～～",
      "汤好喝，，，面香",
      "服务好，环境干净",
      "还不错，就在隔壁经常去吃的。",
      "吃着不错   菜能多点就完美了额",
      "好吃！！！继续光顾！！",
      "环境好。。也好吃。。。",
      "好吃   菜量多点就更好了",
      "具有特色的广东口味，路过来吃了一回，没让我失望！",
      "还行吧！就是种类不太多",
      "还是不错的口味！！！",
      "点的没有了换了别的，一堆洋葱恶心的我吃不下差点吐了",
      "还不错口味，持续开走吧",
      "给家里人过生日选择了这家餐厅，看到网上评价还不错，人气很高，我们吃过了晚餐特意来吃长寿面的，人均消费也不贵，环境很好，还会去打卡的"
    ],
    "CommentCount": 35
  },
  {
    "Item": [
      "肉夹馍",
      "饼卷肉",
      "尖椒肉丝饭",
      "蒜蓉黄瓜",
      "玉米肉饺子",
      "蒜蓉豆芽",
      "香菇白菜肉馅饺子",
      "饼卷菜",
      "韮菜炒鸡蛋",
      "豆腐脑"
    ],
    "Name": "山东味道",
    "Price": 12,
    "Description": null,
    "Address": "东环一路旭日大厦一楼6号铺",
    "lat": 22.648010072706548,
    "lng": 114.05462951324978,
    "Comments": [
      "美味可口，在外吃饭的感觉越来越棒",
      "服务不错，味道蛮好，价格也行，关键是方便，好了，二十个字够了没",
      "肉夹馍没有葱油饼好吃，不送汤，面味道一般，量一般",
      "黑心店，之前去过好几次，味道越来越差劲，食材不新鲜，把过期的包子让人吃，上吐下泻，本以为山东人本分，真差劲，丢山东人的脸。此店必亡！！深恨之。。",
      "跟我妈做的差不多，就是好这一口，家长的味道，来过好多次了，不错",
      "不错，很好！特别喜欢吃",
      "好吃，家乡的味道",
      "很不错，味道很好，价格适中",
      "味道不错，老板娘挺热情的",
      "味道不错，环境也不错，好吃！",
      "山东大包子，吃着不错呢"
    ],
    "CommentCount": 11
  },
  {
    "Item": [
      "港式奶茶",
      "啤酒炸鸡",
      "蜜汁手扒鸡香辣鸡腿堡",
      "咖喱扒翅冰镇可乐",
      "咖喱扒翅送蓝莓汁",
      "香辣小吃",
      "甜品小吃",
      "蜜汁手扒鸡",
      "金桔柠檬茶",
      "藤椒扒翅冰可乐"
    ],
    "Name": "志胜炸鸡汉堡(西田一店)",
    "Price": 12,
    "Description": null,
    "Address": "公明街道西田社区第二工业区商业楼第2栋一楼A08号",
    "lat": 22.80912536388822,
    "lng": 113.90756028266304,
    "Comments": [
      "服务不错，口味比对面好吃，环境还可以，就是希望在忙的时候也要稍微注意一下那个烤翅有没有烤熟之类的，表示上次吃出阴影了有点怕总体来说还是不错的",
      "环境不错，有网络，味道还可以，希望速度可以快一点！！！！",
      "点餐速度快。服务到位，味道也是杠杠的，给个好评",
      "环境还可以吧，里面就不知道了，味道还行，比对面新开的好吃，总体来说可以的",
      "还不错，第一次来吃，应该还不错的吧，好评",
      "环境很好，我女朋友特别喜欢他家的汉堡 ，女朋友说奶油不是很多，很好吃",
      "非常好吃，环境很好，服务态度也很好。欢迎友友们来吃好吃的",
      "敲喜欢这里的汉堡( •̀∀•́ )服务员也态度也特别好",
      "挺好、服务员很热情、态度很好！不错的一家店！",
      "服务可以，味道也不错",
      "很不错！下次还来！"
    ],
    "CommentCount": 11
  },
  {
    "Item": [
      "豉汁蒸凤爪",
      "辣椒",
      "鸡蛋肠粉",
      "牛肉肠粉",
      "斋肠",
      "牛肉蛋肠",
      "瘦肉加蛋肠",
      "双蛋肉饼肠",
      "肉饼肠粉",
      "威记猪杂粥"
    ],
    "Name": "威记肠粉王(翠华花园店)",
    "Price": 12,
    "Description": null,
    "Address": "华丽路2038-5翠花花园底商嘉华中西快餐点隔壁",
    "lat": 22.561385025767525,
    "lng": 114.13858703262616,
    "Comments": [
      "深圳旅行 | 威记肠粉王—看着我长大的肠粉店\n\n这是一家多年的老字号，堪称深圳第一代网红店。读小学的时候对面有一家所以经常吃，可以说它是看着我长大的肠粉店了！以前早上想吃的时候就要提前二十分钟起床，因为总是有很多人排队，怕来晚了就要迟到了，今天路过这里发现这家店竟然还开着！\n\n最爱他们家祖传的秘制酱料，有一种很特别的鲜甜味，肠粉也超级滑，都是用现磨的纯米酱制成，店里还可以看到米浆师傅们不停的在磨喔！肠粉里面的肉也多到我害怕老板亏本，怪不得开了这么多年还是生意那么好～\n\n地址：罗湖区华丽路2046号翠华花园8栋1-01",
      "一直喜欢吃东西不错！！！就是位置不够的！！其他还不错哦(ᵒ̤̑₀̑ᵒ̤̑)哦",
      "饿醒，早起。跑这么远只为吃一顿威记肠粉。深圳冬。好吃好吃好吃好吃好吃好吃超好吃超级好吃。",
      "速度比较快，交通方便，味道还不错。先点个赞。",
      "人好多 味道不错 标准货作业 很不错 值得推荐给大家",
      "这家肠粉是最好吃的怎么吃都吃不够，喜欢吃肠粉的就过来真的是不错选择地址又很好找",
      "最好吃的肠粉，滑而不腻，百吃不厌，上餐速度快，店里环境不错，干净。",
      "好吃✌蛋肠最多点餐的还可以加量品类多多(๑>؂<๑）",
      "高中三年回忆啊，还是原来的味道。只是涨价了而已。好吃",
      "味道很好吃，有空大家可以来常常，很不错的一家肠粉店",
      "东西好吃，只是服务跟不上，东西没吃完也不问一下就收走了，别人多用双筷子也叽叽歪歪",
      "很好吃，适合吃早饭。从翠竹c出口下几分钟就到了，在翠竹学校对面，就是人多",
      "哦兔子在家斤斤计较551155",
      "嘎嘎嘎嘎个规格哈哈哈哈哈哈哈",
      "中产阶级大喊大叫精神的社会活动点击进入酒店接电话电话电话",
      "非常好吃一直都很好吃，真的很好吃，非要20个字。。。。",
      "天天吃，秒杀附近一切同类食品！！！！！！",
      "味道很棒，店面比较小，比较拥挤",
      "生意很火爆，每天都那么多人",
      "就在楼下，老牌子口味不错",
      "第二次来了，很好吃哦！",
      "好吃，好吃，好好吃，深圳最爱肠粉。点个赞！赞！赞(⊙o⊙)哇",
      "天天早餐。味道佳。",
      "点了四分的就是我",
      "加点了三分 好羞耻",
      "每次路过都要来吃，粉很香滑，酱汁靓，喜欢他家的辣酱",
      "是我在深圳吃过的多家肠粉店里的最好的一家，没有之一",
      "很不错，我经常来吃。",
      "꒰⁎❛⃘ͫ&#160;⍘⃘&#160;❛⃘ͫ⁎꒱ 这样的肠粉真心豪华过度， 吃完了一半都觉得自己累的不行。 里面有肉丸， 有猪肝，还有鸡蛋， 可惜鱼片每次都没有。 酱油都堆不进去了， (｡･ˇдˇ･｡) 太夸张。 真心好饱。 价格也不是很贵。不错。",
      "威记肠粉王，威记肠粉王在深圳有好多分店，，很大的招牌，店面分成两间。点了一份猪肝蛋肠，一份叉烧肠。肠衣还是做得不错的，很薄很滑，口感细腻。不过叉烧肠没有什么味道，有点儿柴，所以不太建议。猪肝蛋肠倒是挺不错。肠粉很滑，另外比较薄，可以吃出一层一层的感觉。"
    ],
    "CommentCount": 30
  },
  {
    "Item": [
      "双蛋鲜虾肠",
      "蒜苗回锅肉",
      "斋肠",
      "及第汤",
      "及第汤饭",
      "叉烧蛋肠",
      "双蛋瘦肉肠",
      "早餐炒米粉",
      "滋补鲜虾粥",
      "蒸菜炉"
    ],
    "Name": "威记肠粉王(三及第马家龙分店)",
    "Price": 12,
    "Description": null,
    "Address": "南头街道艺园路148号",
    "lat": 22.555913446401828,
    "lng": 113.93455811904428,
    "Comments": [
      "真的是名副其实的肠粉王 那鲜嫩的肠粉又滑又嫩 真的是回味无穷",
      "很好，环境还不错，上菜速度挺快，味道还可以",
      "口味很好，细腻柔滑",
      "肠粉很不错，口感顺滑，有米香；酱汁味道鲜美，周末必选早餐",
      "服务真的有很多细节没注意到",
      "不错，还是挺好吃的",
      "肠粉打包哥很可爱",
      "味道不错，爽歪歪",
      "最开始是同事推荐，后来就经常来（天天来）。",
      "从小就来吃  你觉得我会不喜欢？"
    ],
    "CommentCount": 10
  },
  {
    "Item": [
      "香辣臊子粉",
      "红烧牛肉粉",
      "香辣肥肠粉",
      "湖南剁椒",
      "鲜汤鸡蛋肉沫粉",
      "牛肉丸",
      "百事可乐",
      "加多宝",
      "花生米",
      "煎鸡蛋"
    ],
    "Name": "陈记筒骨粉",
    "Price": 13,
    "Description": null,
    "Address": "沙井街道万丰村新沙路285-9号",
    "lat": 22.728958972085838,
    "lng": 113.83257728448113,
    "Comments": [
      "这个粉很细很好吃，价格不贵，能吃的好饱哦！",
      "大骨头汤很美味，特别是那个骨髓还有带劲儿，在公交站后边还挺方便的。总之不错啦。",
      "点餐5秒钟，暖胃2小时，的确蛮有味，比x自源的给力",
      "哈哈哈哈哈哈哈哈哈哈哈哈哈哈哈哈哈哈哈哈哈哈哈哈哈哈哈哈哈哈哈哈哈哈哈哈",
      "不错 值得推荐，挺好吃的，的确蛮有味！！！出门5分钟，流汗2小时，vivox9柔光双射照亮厂妹的霉！！！",
      "特别好吃，而且价格不贵，很多东西吃，是吃货都能来尝尝！",
      "很好吃，经常来吃的，米粉很好，汤很鲜，骨头很大",
      "还不错呦，，，经常吃。骨头味道可以。。。",
      "货真价实的大骨汤，汤甜米粉好吃，分量很足",
      "15块的更实惠，13块的分量也很足了",
      "味道真的不错  每次路过都会吃一份",
      "上次点错啦，其挺好吃的。。。",
      "真的不错！这家我经常去吃的，味道好，正宗，基本就是晚上都过去吃宵夜",
      "口:味不错，价格不高朋务质量及卫生条件都很好，下zZ还会去品尝",
      "奔着大骨来的，老顾客了",
      "好吃，份量足，味够劲，冷气足，吃得很舒服强推",
      "很好吃，味道不错，但是量有些少，期待下一次",
      "蛮好吃的，经常不知道吃什么就去他家吃筒骨粉",
      "价格优惠，口味好。",
      "味道很好杠杠的，下次还去吃价格不贵那么大的一个筒骨",
      "味道很好，又有優惠，力",
      "味道不错，筒骨够大",
      "味道很好，下次再来",
      "挺好吃的，汤多粉少～",
      "汤鲜味美，服务热情，",
      "分量足，味道不错",
      "很不错，下次有机会还过来吃！！！！！！！！"
    ],
    "CommentCount": 27
  },
  {
    "Item": [
      "排骨汤面",
      "猪杂汤面",
      "土豆炖排骨饭",
      "烧鸭汤面",
      "辣鸡汤面",
      "肉丸汤面",
      "猪肉丸汤饭",
      "包心贡丸汤饭",
      "尖椒凤爪饭",
      "多味拼盘饭"
    ],
    "Name": "潮汕原味汤粉王",
    "Price": 13,
    "Description": null,
    "Address": "坂田街道坂田社区吉华路传古斋商场1楼101",
    "lat": 22.640017995405245,
    "lng": 114.0685040215079,
    "Comments": [
      "味道好，汤特别鲜，小份才6块钱，有肉猪肝豆腐，分量很足。有风扇，上粉特别快。",
      "很好很好很好很好很好很好很好很好",
      "还不错，挺好吃的，挺不错的，下次还可以再来这边，哈哈哈哈。。。",
      "味道很好。经常来吃。",
      "还行，味道不错，但是店里没有饭，如果有汤饭就更好了。。。。。",
      "好吃(｢･ω･)｢嘿哈哈哈哈哈哈哈哈哈哈哈哈哈哈哈哈哈哈哈哈哈哈哈哈哈哈哈哈哈哈哈哈哈哈",
      "有蚊子在辣酱里味道不怎么样环境还特差失败的地方",
      "空间虽小，环境不错！很多人过来光顾！胜在人心！",
      "味道不错，很多肉！早餐吃完暖暖哒。值得推荐！",
      "非常好，原味汤粉王黄金山活，常久的老顾客了",
      "涂抹哦哦哦哦哦哦哦哦哦",
      "每次都吃，卫生，不错哟",
      "还是不错的啦，是米粉",
      "味道还不错，牛肉丸挺弹，做为胶己人，觉得还行，粿条也可以。沙茶酱不太正宗，很咸。环境也不是特别干净",
      "很好吃，经常光顾，速度快，味道好，棒棒哒……",
      "很好吃，推荐，还会再来的………………………",
      "常去的店，分量多，辣椒酱我很喜欢！",
      "有些事不想说 吃都吃了 汤里有强哥啊",
      "two哦poor哦哦哦的",
      "口味不错也挺实惠",
      "有时间就来吃早餐",
      "口味一般般，每次来吃粉都泡烂了，都是断粉",
      "口味还可以，量太少"
    ],
    "CommentCount": 23
  },
  {
    "Item": [
      "凉拌木耳",
      "红烧鸡块盖浇饭",
      "红烧茄子盖浇饭",
      "葱爆羊肉盖浇面",
      "凉拌三丝",
      "凉拌土豆丝",
      "土豆烧牛肉",
      "凉拌牛肉",
      "兰州炒饭",
      "凉拌黄瓜"
    ],
    "Name": "穆斯林清真中国兰州拉面",
    "Price": 13,
    "Description": null,
    "Address": "艺园路96号",
    "lat": 22.554645215768748,
    "lng": 113.9345580049595,
    "Comments": [
      "还是感觉清真会安心些，每天为吃啥发愁!",
      "新装修。好。可以支付宝，更好。",
      "22套餐盘子里的就4片肉，严重跟图片不符合，但是羊肉泡馍还可以",
      "味道一般般，环境挺好的。味道一般般，环境还行",
      "饭店很干净，汤的味道很足，五星",
      "一点都不好  价格比同行店贵很多",
      "太好吃了，基本是周末必吃的～",
      "挺不错的，每周必来吃一次",
      "周末必须来吃！好吃",
      "服务不错、人很好！",
      "味道还可以   有点贵。",
      "卫生无假最重要！",
      "两人吃个小份大盘鸡，涨死了",
      "面嘛     是 我的最爱。。。",
      "棒棒哒，羊肉泡馍",
      "经常在这吃，很不错！只是优惠相对较少！多点优惠就好了！",
      "一般  价格昂贵"
    ],
    "CommentCount": 17
  },
  {
    "Item": [
      "臊子豆花面",
      "炸酱牛肉双拼面",
      "老北京杂酱面",
      "红烧肥肠豆花面",
      "酸辣豆花面",
      "牛肉刀削面",
      "南瓜饼",
      "红烧牛肉面",
      "老北京炸酱面",
      "凉面"
    ],
    "Name": "豆花面(兴围店)",
    "Price": 13,
    "Description": null,
    "Address": "后瑞社区兴围路29号佳联购物广场旁",
    "lat": 22.64342041654621,
    "lng": 113.83913985538211,
    "Comments": [
      "这里的口味非常不错呢……环境也不错。",
      "宝安石岩-6号线石岩站【宏发世纪城二期】宏发-世纪城项目到达南山桃园约26公里    到宝安约15公里左右  到西丽-科技园约6公里大社区·准现房·都会综合体为梦筑家，载誉而来     78平  约355万/套  3房      88平   约395万/套  3房2厅2卫   88平  约410万/套   4房       107平  约470万/套   4房 2厅 2卫     127平   约570万/套   5房2厅2卫⭕⭕在售产品：78-88-107-127-149㎡，均价4.3－4.5万元⚠【基础信息】占地：45398㎡⛳建面：245429.16㎡ 产权：70年容积率：3.84绿化率：30%总户数：1563车位：1531物业费：3.6元/㎡物业公司：宏发物业【项目价值】区域：宝安、南山、福田聚焦之地，24.5万㎡城市成活区交通：龙大、南光、广深、机荷三纵一横高速路网产品：约78-145㎡户型，准现房，2016年底即可交楼社区：大围合式双子园林、花海泳池、林荫广场等生活配套风格：ART-DOCO建筑风格，彰显品质【专车接送】刘先生：18565609876您身边值得信赖的房地产经纪人。",
      "味道可以，<－biubiu－⊂(`ω´∩)(づ｡◕ ౩ ◕｡)づ第二次来，干拌炸酱面+豆花汤！",
      "味道很不错！已经多次吃了!主要还是很快！",
      "可以，不错，经常来这家吃，非常不错，还吃又实惠，还是四川味，共i赞，好好吃啊",
      "很好吃特别好吃肥肠量很大，能吃饱，最爱吃面，哈哈哈哈哈哈哈哈哈哈哈哈哈",
      "面好吃，好吃，好吃，重要的事情说三遍，三遍，三遍啊。",
      "个人觉得环境很好，吃的也很好吃，总得说是很棒棒的啦",
      "好吃要不上火了，非常好吃，经常光顾，味道美美的",
      "没意思没意思没意思没意思没意思没意思没意思没意思没意思没意思没意思没意思没意思没意思没意思没意思没意思没意思",
      "口味不错，麻辣适中，味道劲爽，美味还再来，么么哒，好吃",
      "很奈斯，适合各种口味的食客。每一个做法都值得尝试……",
      "来这边2年多了，尝试了好多家，就这家的最合口味！",
      "哈哈哈哈哈哈哈哈哈哈哈哈哈哈哈哈哈哈哈哈",
      "经常来，味道不错，服务也挺好的。给个赞！",
      "不对劲啊时间真快开门吗看喝口水你家哪的卡空腹吃贾手机支架就回家在三角形就是看你笑",
      "来很多次了，很合口味。孩子很喜欢酸萝卜和甜豆花。我来当然更喜欢老家的凉粉凉面。",
      "味道正宗，偶尔来换换口味还是不错的!",
      "很多很多很多很多很多很多很多很多很多很多很多很多很多很多很多很多很多很多人",
      "环境好，服务态度热情，口味也好，",
      "挺喜欢来这里吃面的～豆花不错～",
      "非常好～要是种类更多就好了～",
      "吃辣的，这里真的很巴适……",
      "感觉还可以，环境也是一般，在村里做的面还算可以，推荐大家来尝尝",
      "空调开的温度太高，我每次去吃饭都一身汗，29度，20度差不多",
      "味道挺好，很方便",
      "东西不错，川味正宗，爱好川味的朋友们可以来看看，来瞧瞧",
      "麻辣抄手，33°高温都抵挡不了这诱惑！这……巴适。",
      "还不错的店，经常来吃，经常两个人来吃。挺好吃的。",
      "经常来，虽然比最初味道差一点点，但还是蛮不错的",
      "味道不错，值得品尝，强烈推荐。只有错过没有来错",
      "环境卫生干净，味道独特，就是人比较多，要得等，",
      "棒棒棒 非常棒 写满二十字也是很困难 还是非常棒",
      "去过几次了，分量可以，牛肉不错，分也好吃噢",
      "很好吃，建议点细面，多加点芝麻特别的香。",
      "多次光顾了，很好吃，经常来老板很热情！！",
      "很好，吃了n次了，每次不知道吃啥的时候都过来吃炸酱刀削，都是这家店的老客户了，还带我妈过来吃过一次，，么么哒。",
      "感觉很好，每次都是有优惠",
      "周围算是不错的店家了。",
      "经常来了，面nice",
      "行了，味道不错啊！",
      "很不错，经常来吃",
      "你们的包装很赞～",
      "来了好多次：口感很好：住的地方和现在吃饭地方也很远：",
      "带妹妹一起来吃的，还不错，她吃的蛮香的，就是有点辣",
      "很便宜，分量也够，很好吃的明天，还会再来，好评。",
      "环境卫生不错，支持一下，味道也很好，下次再来，",
      "经常来吃，味道挺不错的，老板是四川的，丰俭由人",
      "不喝酒不抽烟不喝酒不抽烟不喝酒不抽烟不喝酒",
      "美味可口，分量充足，值得一吃，吃了好几次了",
      "以前没来过，第一次吃感觉非常不错，下次再来",
      "超级好吃呦，以后还要来，哈哈哈哈哈哈哈哈",
      "好吃哒，经常来吃，刀削面豆花，。。。",
      "味道一如既往的好，口味随选，麻辣酸香",
      "不错不错不错不错不错吧唱吧唱吧",
      "好吃好吃好吃好吃好吃好吃",
      "很好吃，强烈推荐，哈哈",
      "味道很好，每次来都会吃",
      "味道好，份量足。棒！",
      "又麻又辣 重庆人的最爱",
      "还行，来吃过好多次了",
      "好吃不贵老板贤惠！",
      "味道不错，经常来吃",
      "很好吃，经常来吃",
      "服务 和味道都不错",
      "挺好的。天天来。",
      "环境一般，味道还行，川味特色，喜欢麻辣的朋友可以来尝尝",
      "味道非常不错，我就出去吃分量足服务态度好。",
      "口味非常不错。是我来这边吃过最好吃的面了",
      "环境好，服务好，味道也很OK！",
      "不是家乡豆花面的味道，不喜欢",
      "很爱吃他们家，服务员都熟悉了",
      "味道很好！天天晚上来这吃！",
      "味道不错环境不错分量足",
      "味道不错的年，麻辣劲道",
      "牛肉刀削面味道很正宗！",
      "味道很不错，服务也很好",
      "味道不错，服务态度很好",
      "味道非常好我喜欢吃",
      "味道不错，环境优美",
      "味道不错，很喜欢！",
      "现场吃，比外卖便宜好吃",
      "环境不错，味道很好",
      "好吃不贵非常有口味有特色！可以尝试一次！",
      "味道非常的不错，加点辣椒油再加点醋，那酸爽！！你懂的",
      "很好，价钱便宜，味道蛮好的，经常来，蛮多优惠的。。",
      "这里人挺好，面又好吃，老板人也很好，天天来。好吃。",
      "喜欢美食:-O，没得挑剔。非常喜欢吃这里的面。",
      "环境好，服务态度也很好！味道也很不错，面里还有豆花呢！",
      "味道非常好，非常好吃",
      "随机减五元，好！",
      "这里的都方便面，特别好吃，我特别喜欢那个牛肉酱，吃起来真的太好吃了，真是回味无穷啊！这里的环境也是特别不错的服务，也挺热情的，让人感觉很贴心。"
    ],
    "CommentCount": 92
  },
  {
    "Item": [
      "肉夹馍",
      "牛肉凉拌面",
      "青菜拉面",
      "牛肉杂酱面",
      "青椒炒肉盖浇饭",
      "红烧茄子盖浇饭",
      "茄子炒肉盖浇饭",
      "凉拌粉丝",
      "蒜台炒肉盖浇面",
      "香菇炒肉盖浇饭"
    ],
    "Name": "兰州拉面",
    "Price": 13,
    "Description": null,
    "Address": "榕树路23-7号",
    "lat": 22.582858172903745,
    "lng": 113.892400468102,
    "Comments": [
      "这家拉面是我吃的最多次数的一家拉面馆，味道很好！店铺整洁干净！",
      "口味棒棒的。今天又跟朋友来光顾了。口味正宗。汤好喝。",
      "蛮不错的，就是肉量越来越……你懂滴哈 我就不多说了蛮不错的，就是肉量越来越……你懂滴哈 我就不多说了",
      "感觉非常好吃，好吃好不好吃.",
      "蛮不错的，就是肉量越来越……你懂滴哈 我就不多说了",
      "发现清淡简单一点才是我的口味",
      "好好好好好好好好好好",
      "吃了好几次了 还可以",
      "天天涨价有意思不",
      "分量非常足，赞！",
      "来了好几次了，挺不错的，以后还回来，推荐大家也来尝尝",
      "口感不错，卫生也挺好的，经常来这里吃。",
      "价格便宜，分量足",
      "哈。环境还可以可以味道还可以。吃过很多回了。。。。。。。。。",
      "味道很一般 做的太随便了 分量也太少 男生吃不饱的。",
      "好好吃啊哦里咯啦咯啦咯啦咯啦咯啦咯来咯哦老K",
      "味道还行，就是量有点少",
      "太便宜了，呵呵呵。味道还行，价廉物美",
      "好吃啊，就是好吃啊，还怎么好评啊！我怎么凑够20个字呀……够20个字没有哇！",
      "味道的确不错 服务也不错",
      "很喜欢吃，，强烈建议",
      "兰州拉面味还算可以",
      "经常来，味道不错",
      "挺好的！主要是清真！量稍微大一点或放些菜个人意见",
      "哈哈  挺好的吧，该要怎么吐槽呢，，，我也不知道。吃是吃饱了，本来就不饿。吃不下。 就样都不送我天猫券你们好意思吗",
      "兰州拉面中环境比较满意的。不会有羊骚味，饭菜的味道也不错。赞",
      "环境不错，服务也挺好，重要的是好吃不贵。值得一去",
      "泡泡秀 表演15218882896",
      "吃过味道不错哦，有空还去吃",
      "我觉得味道挺不错的。好评",
      "不好吃，还特别贵",
      "常客了 特别好吃",
      "我说了不要洋葱但是还是有洋葱",
      "味道不错，晚上去的 人很少  老板人不错  没空调",
      "----兰州拉面----兰州拉面----兰州拉面----兰州拉面----兰州拉面----兰州拉面----兰州拉面",
      "不错，价钱实惠，制作也好看，有纸巾提供！",
      "差不多都是这个味",
      "ABC得富贵病屏幕发呆太牛了俄法国回家看看坎坷和",
      "嗯，服务不错，味道不错，价格合适，推荐使用。",
      "很不错很不错很不错很不错很不错很不错很不错",
      "好吃、不贵、服务态度也很好，非常棒！",
      "经常来这里吃刀削面哈哈",
      "楼下的店，味道不错～～～",
      "分量多，好吃又不贵",
      "味道好，价格实惠！够新鲜，老板娘又漂亮！"
    ],
    "CommentCount": 45
  },
  {
    "Item": [
      "椰子",
      "椰奶西米露",
      "甜豆花",
      "百威罐装",
      "酱香菜",
      "豆奶",
      "牛肉粉",
      "酸梅汁",
      "可乐",
      "拍黄瓜"
    ],
    "Name": "豆花面(南昌店)",
    "Price": 13,
    "Description": null,
    "Address": "西乡街道固戍南昌第二新村西二巷11号11-3号",
    "lat": 22.587571171116398,
    "lng": 113.86945305533168,
    "Comments": [
      "肥肠面，牛肉面，抄手，份量足足的，关键味道那个正啊，巴实",
      "可以，还没吃呢。我们的生活费的话，超声刀割一样痛苦的话可以吗，",
      "豆花很滑口，牛肉面味道很不错，不会很辣很麻，恰到好处，比较有特色，环境也还OK，桌面都挺干净",
      "豆花面＝豆花＋面。挺新奇的哈，面还行，服务员会根据个人口味进行调整不过要事先说明哦",
      "环境很不错，关键是味道超级好，来吃过好多次了，大爱，老板人也很好哦，超级nice",
      "好吃，跑完步就来吃，味道很正宗，大人小孩都喜欢！吃饱回家，哈哈",
      "牛肉很好吃，汤味道很好，半个月了和室友吃了很多次了。",
      "味道挺不错的，双皮奶好吃，经常来这家店哦",
      "就在家里附近这，第一次来吃，味道不错",
      "很有特色，味道不错，服务态度也很好，桌面地面很干净，比较讲究卫生，下次还来",
      "很喜欢这里的小吃   很好吃",
      "很好吃，伤量多，很",
      "同乐LOL咯谢咯五楼了节快乐JJ么伊卡洛斯拒绝可绝路龙图",
      "店面看起来不错，双皮奶味道不错，，凉皮好硬，不好吃！",
      "味道还好。上次吃还是两个月前的事了。",
      "第一次吃分量挺多的，环境不错",
      "店面卫生很干净，做出来的东西也很干净，看起来很有食欲，吃起来也很香",
      "哈哈哈哈哈哈哈哈哈。不错",
      "喜欢，很好吃，哈哈。",
      "味道不错，环境好。",
      "非常好吃，天天来吃",
      "很好吃，分量很足",
      "挺好吃的，真的。",
      "服务态度不错，值得首选，很安静，女朋友很喜欢。缺点喝的",
      "喜欢吃辣的，可以试试红油豆花，味道还是挺不错的。",
      "好好吃，喜欢这面，欢迎大家来尝一尝 ，环境也很好",
      "环境不错，服务周到，味道好，很好，非常好～",
      "服务热情，太度和蔼，上菜及时，环境愉悦",
      "八块钱，三块排骨，感觉不会再点了",
      "味道不错，挺喜欢吃她家的桂林米粉的，酸辣粉味道有点淡但是还是挺好吃的",
      "感觉一般，作为小吃来说，已经不错了，麻辣确实够味，可惜分量有待提高！",
      "点了牛肉豆花面，味道很不错，面有筋到，牛肉有牛肉的味道，下次还会再来",
      "牛肉面很好吃，豆腐花嫩嫩的",
      "味道很棒，卫生很干净",
      "每天都吃的豆花面，干拌炸酱面是我的最爱，还有不加糖的甜豆花",
      "味道不错，值得推荐",
      "味道挺正，经常在这吃面条，又近。",
      "想吃抄手的，来晚了，没有的卖了",
      "辣，咸，好爽，价格美丽。",
      "阔以推荐推荐，新鲜豆腐花",
      "经常过来吃，味道很喜欢",
      "味道棒棒的，老板人很好",
      "每次都抢到1块红包",
      "老家的味道，不错哦",
      "啦咯啦咯啦咯啦咯",
      "喜欢吃这家，呼呼",
      "可以可以可以可以可以可以，味道不错，经常来",
      "经常来这里吃，味道真心不错",
      "麻辣，口感超到位"
    ],
    "CommentCount": 49
  },
  {
    "Item": [
      "猪油捞面",
      "牛腩捞面",
      "牛腩汤面",
      "蚝油捞面",
      "鲜肉云吞面",
      "鲜虾净云吞",
      "肉酱捞面",
      "蟹籽云吞面",
      "双拼云吞面",
      "蟹籽净云吞"
    ],
    "Name": "詹记云吞面",
    "Price": 13,
    "Description": null,
    "Address": "大鹏新区大鹏街道新乐巷25-1号",
    "lat": 22.599546483494912,
    "lng": 114.48167110678344,
    "Comments": [
      "面店的设计很清新，小店虽然不大，却感觉很温馨，中午12点去吃的饭，天气特别热，本来是没有胃口的，云吞面吃起来确很开胃，面条很细，很有嚼劲，有些薄荷的味道，问了店家才知道这个面是有笕水的竹升面，第一次吃这种面，很新奇的感觉，味道很不错，店里的面种类蛮丰富的，我吃的是虾面，下次再去试其它种类，值得推荐的一个面店，五星好评",
      "大鹏难得的传统云吞面店，面爽口，云吞皮薄馅靓，可惜每天只营业到下午",
      "很棒的云吞店，云吞里面有芝麻吃起来非常的香。",
      "非常非常非常的正宗 好吃 面很滑 云吞很有弹性 每天卖到下午两点就关门 想吃的还得请早呢！",
      "云吞还是那个熟悉的味道，面、米粉比以前好吃了，赞一个！重要的是出餐速度，三分钟就做好了。老板爱你么么么哒",
      "非常正宗的味道，服务很好，值得去吃。",
      "超级棒，很好吃，钟情于蟹子云吞",
      "口淡清淡型，是我喜欢的味道。",
      "还是那个味道！！棒棒的！！",
      "好像三个月没吃到了",
      "净云吞太美味啦！",
      "非常好吃，味道好，馅肉量足，还可以打包生的，自己煮。",
      "好好吃，还有优惠立减活动，我减了两块多，哈哈哈哈",
      "环境不错，味道很好，朋友建议来食的，总体可以",
      "好吃喔好吃.................",
      "味道很好，环境不错，出餐速度快。好好好好",
      "6元吃了个面，口感非常好，下次还会来吃！",
      "很少有的一间专业做云吞的店。店面有点小，但是很干净，服务态度也不错！下次再来",
      "云吞馅和云吞皮手工制作，很不错！",
      "饱满多汁！！！棒棒的！！！！",
      "很好吃，馅料很足很新鲜，十几块钱就能吃得很饱，服务还很nice哦。",
      "吃饱！打包！！！生意兴隆",
      "棒棒的！！！龙岗没第二家",
      "蟹籽好好，鲜虾好鲜！",
      "非常好吃，特别鲜美",
      "我是特地从横岗跑过来吃的……",
      "就是酱紫啦！大鹏云吞的味道！",
      "味道不错 每天早餐都要来两份"
    ],
    "CommentCount": 28
  },
  {
    "Item": [],
    "Name": "清真中国兰州拉面",
    "Price": 13,
    "Description": null,
    "Address": "油园新村北三巷7号",
    "lat": 22.62234116759943,
    "lng": 114.16494652233257,
    "Comments": [
      "味道非常的好，价格也比较实惠，下次还会再来",
      "估计就我过哦了傻X意图律师KTV我有机会来继续啦咯啦咯啦咯啦咯啦咯啦咯啦咯",
      "这家店装修确实好，口味也正宗。如果是在闹市区生意绝对天天爆满。",
      "还不错，速度挺快的，个人觉得兰州炒饭比孜然牛肉炒饭好吃",
      "不错不错不错不错不错不错不错不错不错不错不错不错！",
      "服务周到，味道正宗，卫生干净，装修也不错",
      "炒刀削面味道不行，炒的和拌的一样",
      "很不错 是正宗拉面师傅来的",
      "好吃好吃好好吃好好吃，",
      "蛮不错的！值得过来",
      "葱油饼有点咸，环境卫生不错"
    ],
    "CommentCount": 11
  },
  {
    "Item": [
      "鲜桔柠檬",
      "疯狂烤翅",
      "寒天奶茶",
      "芝士莓果",
      "脏脏茶",
      "波霸乌龙奶",
      "芝士黑提",
      "芒果脏脏",
      "草莓脏脏",
      "超厚芋泥鲜奶红茶"
    ],
    "Name": "午后三点",
    "Price": 13,
    "Description": null,
    "Address": "横岗六约六和路",
    "lat": 22.643779065893497,
    "lng": 114.19769499617988,
    "Comments": [
      "口味非常不错，已经来过好几次了，老板服务热情！",
      "好喝，不错，夏天可以值得来这里消费，大爱",
      "第一次尝试，味道很不错的！点的蜂蜜柚子茶",
      "环境太吵，都很不多",
      "好，很好，非常好",
      "还挺好喝的，也不贵，不错不错棒棒哒，悠闲小吃好去处。",
      "很棒，很棒，很棒很棒很棒很棒很棒，经常来喝",
      "好不错非常好好喝好棒棒",
      "超爱烧仙草，老熟客了"
    ],
    "CommentCount": 9
  },
  {
    "Item": [
      "酿豆腐",
      "萝卜干",
      "腌面",
      "单腌河粉",
      "酿苦瓜",
      "三及第汤",
      "客家盐焗鸡翅",
      "三及第饭",
      "酸甜辣椒酱",
      "邓氏客家三及第"
    ],
    "Name": "邓氏客家三及第(西乡店)",
    "Price": 14,
    "Description": null,
    "Address": "西乡街道圣淘沙骏园11栋7号铺",
    "lat": 22.580162335065243,
    "lng": 113.87012582597194,
    "Comments": [
      "微笑需要真诚，它不是挂在脸孔上的一种装饰品，也不是肌肉的一种无意识的运动，而是内心真情实感的自然流露，只有真诚的微笑才是最美的，也只有真诚的微笑才能打动人。",
      "天氣冷就想過來吃，它的三及第湯好喝，米粉也不錯。來很多次了。环境也算乾淨。",
      "感觉不错，来了几次了，三及第味道很好，推荐",
      "小店环境整洁，工作午餐的首选。就爱这口，常和同事去。分量也很足，男士都够。",
      "非常不错，味道正宗！每周都会过去几次的！值得推荐！.",
      "客家的汤好。面的话太干了点。以后还会去的。",
      "份量足上菜快，口味不错，能再优惠些更好。",
      "好吃，味道棒棒的。。。喜欢的味道",
      "很亲切的一家餐厅，味道也很好！",
      "很好，味道也很好，服务也好好",
      "味道不错，我男朋友很喜欢",
      "有点小贵，口味不错",
      "生菜还要再洗干净点",
      "放手吧都觉得你吃就吃看到你设计额含蓄点都觉得就到家",
      "在这里消费好贵哦"
    ],
    "CommentCount": 15
  },
  {
    "Item": [
      "陈记三及第",
      "咖喱牛腩饭",
      "冬菇焖鸡饭",
      "花生猪脚饭",
      "枸杞叶",
      "客家焖猪肉饭",
      "冰糖豆花",
      "英潮牛肉辣椒酱",
      "红烧排骨饭",
      "梅菜扣肉饭"
    ],
    "Name": "陈记三及第(笋岗店)",
    "Price": 14,
    "Description": null,
    "Address": "宝岗路168号(平安银行对面)",
    "lat": 22.574158009070633,
    "lng": 114.11903496405519,
    "Comments": [
      "在笋岗，环境不错，口味不错，点了三及第汤饭，可以加饭哦！准备离开深圳了，以后有机会还来吃。",
      "不同于家乡的味道，但是很好吃，汤里的肉也很多。",
      "第一次来深圳，第一次来这儿吃饭，感觉还可以",
      "好吃，味道正宗，吃的放心，吃的开心。",
      "口味比较淡，不用担心油的问题，除了三及第还有其他菜可以选择。",
      "饭菜比较养生营养，环境也干净卫生的！很有食欲！",
      "又好吃又便宜，今天还有活动，太太太值了。",
      "非常好吃，来了好几次了",
      "好吃，量大，很值",
      "店面较小，枸杞叶有点老，蒜蓉酱没别家香。一般吧。",
      "好吃，量足，还有折扣，我喜欢",
      "一般，蒜泥酱没别家好",
      "还不错，料很足！"
    ],
    "CommentCount": 13
  },
  {
    "Item": [
      "牛腩面",
      "杂酱粉",
      "老麻抄手",
      "麻辣鸡丝凉面",
      "泡椒肥肠面",
      "重庆杂酱面",
      "西红柿鸡蛋面（粉）",
      "重庆小面",
      "炸酱面",
      "泡椒鸡杂面（粉）"
    ],
    "Name": "一碗小面",
    "Price": 14,
    "Description": null,
    "Address": "民兴路东泉新村56栋1号",
    "lat": 22.628930641164352,
    "lng": 114.03670670138172,
    "Comments": [
      "超级好字数 老板人超级好 面好吃 店干净 特意跑好远去吃",
      "一碗小面家的面真的很好吃，特别是杂酱面和酸辣粉",
      "牛腩面，肥肠面，肉丝面，面有弹劲。我的最爱。",
      "面的味道确实不错，材料真实，口感好，服务一般，环境也一般，",
      "挺好的，味道很不错，在这里吃了好多次了，强烈推荐",
      "味道很纯，食材很好，油也不错，值得推荐",
      "基本每天都来吃，实惠，味道也不错",
      "挺好的，味道正宗，有家乡的味道",
      "味道，环境都非常棒，牛腩面不错",
      "味道鲜美，很棒的一次体验",
      "一般，吃不饱，环境还好",
      "环境，味道都挺好的推荐",
      "好吃。还是原来的味道",
      "太慢了不会来第二次了",
      "挺好的，味道，环境",
      "很棒！！很好吃！！",
      "挺好的，基本每天都会在这吃一顿",
      "还可以噢，挺干净的",
      "去深圳玩的时候住在的酒店后面发现了这家小店，娘俩一起工作，老板娘热情开朗，还不错！",
      "红油抄手，好吃！",
      "口味不错，我吃稍微有点咸",
      "味道很好，值得推荐",
      "挺好的，味道超级棒",
      "挺好的，味道，份量"
    ],
    "CommentCount": 24
  },
  {
    "Item": [
      "哈尔滨红肠",
      "哈尔滨啤酒",
      "拌干豆腐丝",
      "红油耳丝",
      "维他柠檬茶",
      "东北熏鸡",
      "怡宝矿泉水",
      "百事可乐",
      "加多宝",
      "雪碧"
    ],
    "Name": "东北水饺店",
    "Price": 14,
    "Description": null,
    "Address": "桃源街道平山路131号",
    "lat": 22.5891064638941,
    "lng": 113.97522573627852,
    "Comments": [
      "量多价格实惠，值得购买！推荐好吃。",
      "喜欢东北的味道，这家店很好吃，今天是第二次来的，真挺好的",
      "好吃，经济实惠，东北味道，老板人也不错！",
      "味道杠杠的，贼好吃咯！下次还会光顾！",
      "口味还是很好的～芹菜和香菜特别赞～",
      "地道，新鮮，親切，好吃 !",
      "吃到了家里的味道",
      "口味还可以，饺子皮儿挺筋道，应该还会再来，只是加汤要多加一元是什么道理？应该可以送汤喝吧",
      "我一直来这家店吃饺子"
    ],
    "CommentCount": 9
  },
  {
    "Item": [
      "猪杂鱼丸汤饭",
      "猪肉丸猪杂汤粉",
      "鱼丸鲜瘦肉汤桂林米粉",
      "腐竹烧肉饭",
      "猪肉丸汤河粉",
      "猪杂河粉",
      "猪杂汤桂林米粉",
      "猪筒骨汤饭",
      "三丸汤",
      "猪肉丸肉饼汤饭"
    ],
    "Name": "原味汤粉(华强北店)",
    "Price": 14,
    "Description": null,
    "Address": "华强北路曼哈顿美食城9号铺",
    "lat": 22.551756543569116,
    "lng": 114.09597627009663,
    "Comments": [
      "出锅速度快，口感还行，买的牛肉丸，还不错，不过其它料不多",
      "差评，真的是，我肚子饿的要命叫了个烧鸭饭，然后坐到一旁的桌子，等了半天饭还没到，我就纳闷了过去问她，结果她说饭就放在一张空桌子上，她们也在纳闷人呢？就这种服务质量，做事方式，差评。。。。这个时候根本没什么人吃饭，就两三个人，她们居然能把饭菜放在一空桌子上任风扇吹凉了，我中间还故意望了收银员几眼，她也看到我了……想想就恼火…还是少点去这里吃好了，这么不用心的服务，估计东西也很难保证质量",
      "味道不错，就在办公楼下，经常过来吃，一般都不用等，5分钟内就有吃的",
      "真的很好吃啊，吃过一次就忘不掉，天天想吃，所以基本天天来",
      "味道很好吃，午饭都来这里觅食，离公司很近很方便。",
      "饭不错  挺好吃哒  那天刚好饿了   我点了猪杂汤饭，好吃吃，盘子清了   没图真的好吃",
      "挺好吃的，就是环境太一般了，特别是那个泪牛满面",
      "很好很好，经常吃了，不错不错不错不错不错不错！",
      "可以的，份量很足，味道也不错",
      "不错，很合我的口味！",
      "非常好吃的原味湯飯，是家響口味，吃著有家的感覺，想家了……",
      "还不错，味道比较好",
      "湯底不錯，分量也足",
      "好吃好喝好服务。",
      "很好吃的猪杂河粉",
      "味道扛扛的，这个味道我喜欢，伤量足，味道又好吃，超赞",
      "上班经常在这里吃，很适合我的口味，不错的一家！",
      "只要自己没做饭吃，就来他家，味道很不错",
      "吃了个早餐，分量足，但味道有点淡。",
      "吃完好多痰，不知道1添加了什么鬼",
      "味道不错，价格实惠，老顾客了。",
      "不错，味道好，吃了好几次了",
      "呵呵呵呵呵额呵呵呵呵呵呵呵",
      "可以！挺不错的！汤好喝",
      "服务态度很好，味道也不错，很好吃，下次还会再来吃！",
      "味道非常鲜美，流连忘返，回味无穷，强烈推荐",
      "666，没话说，吃了一年多了",
      "煮汤粉的小弟好6阿！快准狠",
      "经常来吃的，已经吃了几年了",
      "走过路过，看看试试。",
      "汤味道可以 上菜速度快",
      "还不错，味道很好",
      "口味不错，经常来",
      "垃圾，味精下很多，吃完非常口渴",
      "口味不错哦~经常来这家店吃。",
      "不错很好吃很好吃很好吃",
      "很满意美味极了，下次带朋友们一起来吃。给力啊!",
      "很好，不错，下次还来",
      "个人觉得味道很不错，服务也很好",
      "味道还可以，不错，去吃看看，，"
    ],
    "CommentCount": 40
  },
  {
    "Item": [
      "榨菜肉丝饭",
      "凉瓜炒肉饭",
      "咸鱼茄子饭",
      "土豆片回锅肉饭",
      "莴笋炒肉饭",
      "雪里红肉沫饭",
      "景田纯净水",
      "尖椒荷包蛋",
      "凉拌西红柿",
      "可乐"
    ],
    "Name": "湘竹人家(松园南街店)",
    "Price": 14,
    "Description": null,
    "Address": "松园南街30号",
    "lat": 22.55806492716725,
    "lng": 114.11262113907203,
    "Comments": [
      "还送了一个海带汤，真的很棒。海带汤里面还有一块肉。貌似还有鸡蛋呢！汤不错。开胃小笋的分量也很多。",
      "味道很正；价格合理；每天都想到这里来吃饭！",
      "很辣，喜欢辣的朋友过来吃，",
      "菜品种类丰富，有地方特色，菜的味道做的不错，上菜速度快，服务好",
      "物美价廉味道还是不错的，和几个朋友一块，不失为附近的一个好去处",
      "味道还行，，服务很一般",
      "上菜快，味道不错",
      "比较不错！味道偏咸点！其它可以！比较静！吃了很多次了！",
      "价格比之前贵多了，菜分量少了，希望之后加点服务",
      "上菜速度快，老板也挺好，只是建议把汤经常换换",
      "哦里咯啦咯啦咯啦咯啦咯啦咯啦咯啦咯啦咯厉害",
      "店面不大，味道还算可以把，这是第二次吃了。",
      "饭菜可以，水煮鱼也便宜，就是油烟味太重点",
      "进去感觉臭臭的，再也不会去光顾了",
      "肻就是了、巡。。。。。。。。。。。。。。。。。。。。。。。。。。。。",
      "可以再实惠有汤就好了",
      "价格实惠，饭量足等",
      "菜很合胃口，不错",
      "很好！希望大家多来来来！",
      "就是贵。涨价太厉害了",
      "味道不错，量有点少",
      "好，很好，非常好",
      "份量多点就更好了",
      "味道还不错湘菜。",
      "湘菜不错，挺辣，挺入味，也不算特别贵，特别酸菜鱼之类的分量大，饱饱的",
      "还可以  点了好几次",
      "口感不错，很实惠",
      "服务一点都没有  不是不好  而是没有",
      "经常去，菜还是挺湖南风的，不错！也很实惠",
      "位置不错，味道还行，经济实惠，还好吧",
      "一直在这家吃，味道很不错！",
      "评价过了，还挺烦人"
    ],
    "CommentCount": 32
  },
  {
    "Item": [
      "肠粉",
      "猪杂汤河粉",
      "猪杂汤饭",
      "排骨手工面",
      "排骨汤米粉",
      "猪杂汤手工面",
      "家猪肉炒米粉",
      "家猪肉炒手工面",
      "家猪肉炒河粉",
      "荷包蛋"
    ],
    "Name": "万景潮州面馆",
    "Price": 14,
    "Description": null,
    "Address": "彩田南路万景花园商铺",
    "lat": 22.566720674942562,
    "lng": 114.07355426813417,
    "Comments": [
      "不好吃不好吃不好吃不好吃不好吃不好吃不好吃",
      "肠粉好吃 汤料不像有的地方就是酱油的味道 非常香 老板态度也好 人均15",
      "牛肉丸面，15块钱，两碗，，很喜欢，好吃好吃，经常来吃",
      "实惠又好吃，物美价廉，每天都会过来吃欢迎大家过来品尝",
      "肠粉好吃，好好好好好好好好好好好好好好好好好好……",
      "很好吃，还实惠，饭粉面都有，每天午饭都是这解决",
      "好多人，味道还可以。排队也有秩序，店内的工作人员都好忙好忙。为了20字，也是不容易。",
      "味道不错，牛肉丸很正宗，和同事们经常来吃。",
      "牛肉粉超好吃，价格便宜分量足，上餐速度也快，2分钟搞定，就是辣椒酱有此少",
      "老家口味，很正宗，可以推荐前往",
      "干净卫生，味道美，，，，，，，，干净卫生，味道美，，，，，，，，干净卫生，味道美，，，，，，，，吃过很多次了。",
      "菜有点咸，答应给我多点青菜，又不给。不过为了拿券，还是评论一下把。",
      "口味合适，服务周到，客气，环境洁净卫生，价格比较优惠，值得推荐！",
      "好吃好吃好好吃好好吃好好吃好好吃好好吃好好吃好好吃好好吃好好吃",
      "环境优雅，服务热情，菜品味道不错，会给身边的亲朋好友们推荐的。",
      "口味佳，服务好，环境优雅，以后会常来，也会给身边的朋友们推荐。",
      "挺实惠的  味道也还行，服务也可以，环境也不错。图文不符系列 嘿嘿",
      "可以可以可以可以可以可以可以可以可以可以可以可以可以可以",
      "汤很好喝，份量也很足，还有好多肉，也便宜，经常吃了",
      "一般般吧！希望在改进下服务，但是味道还可以，就是服务的问题，性价比也不错，但是点大份就很亏",
      "好吃，经常买，好好好好好好好好好好好好好好好……",
      "很好嗯的，每天早上都来吃，欢迎打架也都来吃",
      "交通便利，有汤粉也有米饭。生意火爆，最关键的是觉得附近的地方就这家菜的口味比较好。",
      "人很多，价格实惠，做的也可以，值得推荐。",
      "不错，不错，不错，不错，不错，不错，不错，不错，不错，不错，不错，不错，",
      "环境好，服务佳，口味很合适我，下次还来光顾，也会给身边的亲朋好友们推荐！",
      "好吃又实惠，在这边12一荤两素很便宜了，还有汤粉很好吃，几乎每天都来吃",
      "感觉蛮好吃的，环境和卫生都可以。主要是汤河粉里面的汤很正宗。要赞一个。",
      "非常好的，非名字仔仔细细地去",
      "非常喜欢吃，今天第二次来，以后也会经常来。特别喜欢吃宽粉",
      "面很不错，配料都是现场做的，非常新鲜，难得吃到这样的",
      "是地道的广东口味，服务热情，环境也干净，下次还会来。",
      "料很足，又很实惠，经常去吃，来这两年了，也吃了两年",
      "口感不错，经济实惠，有快餐，粉，面，非常适合上班族",
      "正宗广东风味，我很喜欢，环境也很干净，下次还会来。",
      "量足味道好，特别吃饭最划算。比较经典的潮汕口味。",
      "附近也没有多少吃的地方 在这都吃了好久 都快吃腻了",
      "每天来吃肠粉的人排长龙，店家服务态度好，不错。",
      "味道不错，分量够足，12块钱最低，在市中心这一段，相对来说，是很不错了，汤底也好。",
      "周一到周五都在这里吃，吃不厌，便宜而好吃！",
      "这家店的猪杂河粉很好吃~很正宗的潮汕粿条",
      "。。。。。？。。的$*$回家吃饭#回家黄",
      "很好吃，，以前只是听说  第一次来吃。，，，",
      "味道十分正宗，服务也特别到位，地理位置十分宽敞，空气流通，值得一赞。。。",
      "还可以欧味道不错鸡肉味道很好欧",
      "味道不错 老板人很好 店面环境舒服",
      "服务态度很好，味道不错",
      "拿了卡还说我没给，操蛋",
      "活动很多，超好，给力，",
      "粉很好吃，每周必吃的",
      "实惠～～不过饭菜有点咸了～汤粉也很油腻～～不过胜在味道还不错",
      "吃几个月了，可以可以吃几个月了，可以可以吃几个月了，可以可以",
      "好吃，潮汕菜，首选",
      "还不错，速度挺快的，还送饮料，和同事们一起来的，都挺满意",
      "味道好。价格合理，干净，比其他地方好多了，我感觉真的可以",
      "味道不错，这家店早中晚餐都有生意很好，好多人排队去吃！",
      "俺家附近味道很不错性价比很高的一家潮州粉面店，很满意",
      "肠粉还是不错的，挺好吃的，过一段时间还会换材料挺好的",
      "还挺不错喔，我吃的是饭，感觉味道偏咸，但是合我胃口",
      "伙食种类多，味道也不错，价钱也很合适，用餐环景舒适",
      "好吃，经常买的，好好好好好好好好好好好好好好好……",
      "很好吃，价格也很便宜很公道，以后上班会经常来吃。",
      "好吃，天天吃，老板娘人好，这几天支付宝还有优惠",
      "味道是真心不错的，不是经常去吃，因为没有空调",
      "好吃又实惠，老板娘人好，有饭有粉，极力推荐",
      "好吃还很快，挺实惠的也不会油腻腻的，挺好",
      "好好好好好好好好好好好好好好好好好好好",
      "还不错哦，同事推荐来的，菜炒得不错",
      "吃过他家的粉，第一次试面，挺好吃。",
      "还可以 就是有时候分量多 有时候分量少",
      "牛肉丸比较正，年份量没有去年多了。",
      "价格还算合适，味道也还不错，服务有待提高，出餐速度有点慢，有时候等好久！！",
      "好吃实惠，粉……哈哈哈",
      "天天吃，很好很好很好吃",
      "非常好吃，正宗潮汕口味",
      "很好吃，分量也很足。",
      "挺好的，离的近很方便",
      "天天去吃，炒鸡好吃",
      "环境好，卫生，推荐",
      "很好，超赞喔……",
      "没有红包，不高兴",
      "还好吧，面不错，",
      "早餐肠粉比较好吃",
      "味道很正，一直很喜欢，吃了三年了……继续支持",
      "以前觉得很好吃，现在的河粉越来越难吃，不新鲜",
      "味道很不错，可以来哦。想来的话就可以哦。",
      "口味不错，价格也非常优惠，真心好赞推荐。",
      "喜欢！味道也不错！商家笑容挺甜！",
      "人很多，味道不错，就是会呢没坐",
      "还不错，只是肉真的不多",
      "不错 ！味道不错，是我喜欢吃的味道，！！，",
      "不错，油足，饭量足！菜足！适合上班族",
      "很好，经常去的这一家超赞",
      "开车过去大概十五分钟，但是感觉很好"
    ],
    "CommentCount": 94
  },
  {
    "Item": [
      "土豆丝捆粿",
      "炖汤",
      "猪肉鸡蛋肠粉",
      "潮汕粿肉",
      "香芋捆粿",
      "鲜虾鸡蛋肠粉",
      "酸菜捆粿",
      "菜脯捆粿",
      "玉米捆粿",
      "韭菜捆粿"
    ],
    "Name": "诚记潮汕肠粉",
    "Price": 14,
    "Description": null,
    "Address": "南山街道南新路南山村北东巷62号-2",
    "lat": 22.521137938806476,
    "lng": 113.91976313419819,
    "Comments": [
      "来吃差不多半年多了，几乎每晚都会过来点一份肠粉，鸡蛋牛肉最贵，但也最好吃，量很足！",
      "很喜欢的一家肠粉店，最喜欢的是牛肉肠，经常来，唯一不足就是酱汁的水平忽高忽低 ，辣椒酱很香，有点辣～",
      "熟地汤很够味，料足。牛肉肠粉味道也很好，果能薄一点更好",
      "肠粉味道不错 一次吃了两份 下次还会再来",
      "价格有点贵...........",
      "很不错的肠粉，料足。就是小贵",
      "非常好吃的肠粉！非常好吃的肠粉！非常好吃的肠粉！",
      "非常好吃的肠粉！真的很好评哦！！！！！！！",
      "非常好吃的肠粉！非常好吃的肠粉！经常去吃！",
      "非常好吃的肠粉！好吃不贵！",
      "味道很好，份量够",
      "不错，他家的肠粉还是挺好吃的哦。下次再来",
      "大家快来吃，好吃又优惠，很大一份哦",
      "份量很足，一个肠粉加个捰粿饱到不行",
      "不错，挺喜欢他家的汤粉",
      "超级好吃！价格实惠！",
      "味道相当相当的不错，超级好吃，每次下班之后都会来这里吃上一个再回家，老婆也总叫我每天帮她带一个回去很赞",
      "不错 喜欢吃 每次唱完个就来吃 盆友也很喜欢 赞赞",
      "非常好吃的肠粉！！！",
      "非常好吃的肠粉！",
      "来吃差不多半年多了，几乎每晚都会过来点一份肠粉，鸡蛋牛肉最贵，但也最好吃，量很足！",
      "很喜欢的一家肠粉店，最喜欢的是牛肉肠，经常来，唯一不足就是酱汁的水平忽高忽低 ，辣椒酱很香，有点辣～",
      "熟地汤很够味，料足。牛肉肠粉味道也很好，果能薄一点更好",
      "肠粉味道不错 一次吃了两份 下次还会再来",
      "价格有点贵...........",
      "很不错的肠粉，料足。就是小贵",
      "非常好吃的肠粉！非常好吃的肠粉！非常好吃的肠粉！",
      "非常好吃的肠粉！真的很好评哦！！！！！！！",
      "非常好吃的肠粉！非常好吃的肠粉！经常去吃！",
      "非常好吃的肠粉！好吃不贵！",
      "味道很好，份量够",
      "不错，他家的肠粉还是挺好吃的哦。下次再来",
      "大家快来吃，好吃又优惠，很大一份哦",
      "份量很足，一个肠粉加个捰粿饱到不行",
      "不错，挺喜欢他家的汤粉",
      "超级好吃！价格实惠！",
      "味道相当相当的不错，超级好吃，每次下班之后都会来这里吃上一个再回家，老婆也总叫我每天帮她带一个回去很赞",
      "不错 喜欢吃 每次唱完个就来吃 盆友也很喜欢 赞赞",
      "非常好吃的肠粉！！！",
      "非常好吃的肠粉！"
    ],
    "CommentCount": 40
  },
  {
    "Item": [
      "干拌全家福面",
      "干拌木耳肉丝面",
      "干拌排骨面",
      "干拌肥肠面",
      "干拌红烧牛肉面",
      "景田",
      "干拌红烧牛肚面",
      "干拌麻辣牛肉面",
      "干拌酸豆角肉末面",
      "炸酱面"
    ],
    "Name": "湖南牛肉粉",
    "Price": 15,
    "Description": null,
    "Address": "西丽街道新光路103号一1",
    "lat": 22.582152273657798,
    "lng": 113.95855968344887,
    "Comments": [
      "挺好吃的，店里有空调，吃了，还可以休息一下。",
      "味道很好，就是小碗分量又点少，下次换大碗",
      "还挺好吃的哈，一碗都可以吃撑的那种。",
      "来了好几次，都吃的很饱",
      "很正宗的常德牛肉粉，经常过来吃，老板人也很好。",
      "非常好吃，老板人很好",
      "红烧牛肉粉特别好吃",
      "挺好吃的，非常不错，这回是炒粉",
      "面条不错，服务很好",
      "用支付宝还可以优惠，太不错了，给力！"
    ],
    "CommentCount": 10
  },
  {
    "Item": [
      "小面",
      "砂锅牛肉粉",
      "砂锅肥肠粉",
      "罐装可乐",
      "罐装雪碧",
      "天地一号",
      "青岛啤酒",
      "椰子汁",
      "红烧茄子",
      "红烧牛肉面"
    ],
    "Name": "成都名吃(蛇口店)",
    "Price": 15,
    "Description": null,
    "Address": "公园南路16号",
    "lat": 22.493581139908354,
    "lng": 113.93151928625086,
    "Comments": [
      "好吃，口味很成都，价格很优惠，地理位置适中~",
      "各方面都还基本满意。点的菜上错了没跟店家计较，将就吃了。服务态度蛮好。",
      "味道很不错，喜欢",
      "稳定了，嗨皮好的。不错不错，还回车键。还会避开。还会再来",
      "挺好吃的，每次都是点他们家的",
      "不错，手机支付宝还有折扣",
      "味道还行，四川口味。",
      "路边店，味道好的很",
      "味道各方面还可以！",
      "经常去，味道很好",
      "味道没有以前那么好吃了！",
      "泡椒猪血，好吃，够辣够酸"
    ],
    "CommentCount": 12
  },
  {
    "Item": [
      "土豆红烧肉饭",
      "凉瓜牛肉饭",
      "凉瓜肉片饭",
      "包菜回锅肉饭",
      "土豆炒肉丝饭",
      "外婆菜炒肉饭",
      "豆豉鲮鱼麦菜饭",
      "小炒茄子肉沫饭",
      "三鲜汤",
      "凉拌西红柿"
    ],
    "Name": "湘竹人家",
    "Price": 15,
    "Description": null,
    "Address": "东门南路金城大厦五座大堂106A",
    "lat": 22.54901397098795,
    "lng": 114.12856203296867,
    "Comments": null,
    "CommentCount": 0
  },
  {
    "Item": [
      "萝卜干",
      "凉拌黄瓜",
      "萝卜皮",
      "酸豆角",
      "小咸菜",
      "麻辣牛肉粉",
      "红烧排骨粉",
      "牛腩河粉",
      "辣萝卜",
      "红烧猪蹄粉",
      "银耳莲子糖水",
      "凉拌海带丝"
    ],
    "Name": "常德牛肉米粉",
    "Price": 15,
    "Description": null,
    "Address": "广东深圳福田区车公庙安徽大厦负一楼",
    "lat": 22.542333001327204,
    "lng": 114.03775502391152,
    "Comments": [
      "好！（此评论虽然才1个字，但语法严谨，用词工整，结构巧妙，琅琅上口，可谓言简意赅，足见评论人扎实的文字功底，以及信手扭来写作技巧和惨绝人寰的创造能力，实在佩服佩服，再加上以感叹号收尾，实在是点睛之笔）。",
      "真的超爱这家，在深圳吃的最正宗的常德牛肉粉了，强烈推荐，最爱牛腩粉和牛肚粉。",
      "别人推荐的说还可以，办公室周围的快餐店里头还算可以吧，上班偶尔吃一次，有时候有些食材感觉一般",
      "一家三口服务态度很好 正宗常德米粉 以后会经常光顾",
      "经常来这里吃，味道不错啊(⊙o⊙)(⊙o⊙)(⊙o⊙)(⊙o⊙)",
      "非常飞诚好吃，下次一定再来，一定再来，如果有机会的话，真的。",
      "没得吃，才选择的",
      "在公司楼下面，今天下雨就去看看，三鲜面，人很多，好吃方便",
      "味道不错，就是关门太早了，老板晚上六点就收档了",
      "经常吃，湖南口味，凑齐二十字，二十字，二十字",
      "经常吃，凑齐二十字，二十字，二十字，二十字",
      "味道好很好吃料很足服务很好 速度快赞赞赞哦",
      "哈哈哈哈哈哈哈哈哈哈哈哈哈哈哈哈哈好好好",
      "正宗的湖南口味，正宗的常德米粉",
      "哈哈哈哈哈哈哈哈哈哈好好吃",
      "每次来车公庙都来吃一碗再走",
      "不错很好吃推荐去吃",
      "经常来吃的米粉店，味道很接近老家的了，不错。",
      "味道还行，不错，可以再来吃，值得推荐哈！",
      "还没吃呢，不过看起来比较干净",
      "味道很好，经常吃",
      "就当工作餐吃而已，对味道就不要要求太高了"
    ],
    "CommentCount": 22
  },
  {
    "Item": [
      "紫薯粉粿",
      "叉烧肠粉",
      "潮汕粉粿",
      "韭菜粉粿",
      "银耳糖水",
      "小鼠壳粿",
      "香芋粉粿",
      "普宁捞面",
      "卡通包子",
      "猪杂丝"
    ],
    "Name": "普宁阿肥肠粉",
    "Price": 15,
    "Description": null,
    "Address": "华强北路419栋曼哈美食广场",
    "lat": 22.55179809853935,
    "lng": 114.09414471499294,
    "Comments": [
      "挺好吃的，味道正宗，在深圳很少能比这家再正宗了！支持支付宝花呗付款！非常方便！个人比较喜欢在店铺里吃，感觉比较干净而且份量好像更足",
      "选的鲜虾肠粉，上餐很快，不过跟广州吃的不太一样，味道还可以。",
      "味道还可以 下次有时间再来吃 就是有点慢 时间",
      "非常好，，一直关顾的一家店，，，，，，经典好吃，汤味浓！粉很劲道！！",
      "份量蛮多，味道也挺鲜美，与广州吃的差不多，找到感觉了",
      "不错 推荐来吃一下 牛肉分量很足 虾也不错 味道超赞",
      "这家肠粉味道很好，份量很足，好吃又不贵，真正实惠，我经常到店面吃。",
      "嗯嗯，很不错，价格也很实惠，吃过很多次了，跟家里的口味一样",
      "曼哈美食广场这边的，环境一般吧，味道还行，以后再来咯！",
      "好好好好好好好好好好吃吃吃吃吃吃吃吃吃吃",
      "好吃好吃好吃好吃好好吃好好吃哦！好好吃",
      "正宗味道，很好吃，老板很好说话",
      "存条劲，我还能说什么，不吃的话，你这辈子就是白活了，来吧，要死而无憾",
      "好吃！！！！！推荐大家试试",
      "好吃，地道的家乡口味",
      "味道不错，服务到位",
      "好吃，就是太贵。",
      "还行，就环境不咋样。。。。。。。。。。。。。。。。。。",
      "口味一直不错，味道正宗，堂食份量更足",
      "正宗普宁肠粉，强烈推荐！",
      "还蛮好吃的，吃过几次了",
      "可以吃了好多次了",
      "味道很好，很不错！汤足料汁足！",
      "很好吃，经常过来这里吃肠粉。",
      "很好，不错，下次还来",
      "还不错 就是量少了点",
      "不错，味道棒棒的",
      "味道不错，环境干净",
      "味道好，环境不错"
    ],
    "CommentCount": 29
  },
  {
    "Item": [
      "杂锦汤面",
      "海鲜豆芽菜汤",
      "猪肉丸汤河粉",
      "自制剁椒",
      "猪杂益母草汤",
      "杂锦汤河粉",
      "猪杂海鲜汤面",
      "炒饭",
      "炒米粉",
      "杂锦汤桂林米粉"
    ],
    "Name": "孙记汤粉面",
    "Price": 15,
    "Description": null,
    "Address": "下梅林河背村78号",
    "lat": 22.569828756718486,
    "lng": 114.04945689046393,
    "Comments": [
      "吃饭吃饭吃饭吃饭，非常非常非常红红火火恍恍惚惚，好好好，值得推荐",
      "不大的一家店。经过容易忽略。每天都经过都没有进去吃，觉得还挺好吃的，平时很多人。老板娘态度很好，很温暖。这边的汤粉肉好多价钱很公道，平时很多人来吃的，酱也是非常鲜美的。很喜欢这种实在的小店，不少回头客。",
      "老客户了，很好吃的啦，支持大家多多捧场。",
      "好好好，，，值得推荐，，，味道不错，，，还好还回来还回来还好啦",
      "一直喜欢这里的口味，东西很好吃，希望一直保持。",
      "真材实料 新鲜好吃!",
      "味道不错价格实惠，环境也可以，服务态度也不错",
      "好吃，老板人好好，差不多每天都会去。",
      "还可以哦，有空调，东西也多，吃得饱，重要的是听着潮汕话很亲切",
      "味道很好。炒河粉一般。",
      "回味个人认为可以，吃了以后感觉味道好，方便，快来吧！！！",
      "经常吃的汤粉店，味道清淡非常适合清淡口味的朋友们。",
      "老板人很好，热情的服务，料足！敲好次！！！",
      "东西超级好吃。老板人超级好。便宜有又实惠。",
      "不错，比较喜欢，货真价实，服务态度也很好！",
      "老板帅气，每次量都给这么多，真的敲好次！",
      "真的好好吃，有优惠连着吃了三天啊！",
      "好吃，吃了好几年了，汤特别好喝",
      "味道个人感觉好。口味适中。",
      "口味不符合吧，感觉不好吃",
      "好吃，料多，辣椒超级好吃",
      "很好吃，老板人很好。",
      "老字号，味好，料足",
      "挺好，常来，好吃。",
      "空调店铺，凉爽吃潮汕老家河粉，好吃好口味",
      "价格实惠，好吃*^_^*"
    ],
    "CommentCount": 26
  },
  {
    "Item": [
      "竹笋猪肉煎饺",
      "凉拌青瓜",
      "白粥",
      "韭菜鸡蛋煎饺",
      "猪肉小笼包",
      "猪肉锅贴",
      "韭菜肉煎饺",
      "酸菜肉饼",
      "玉米猪肉煎饺",
      "皮蛋瘦肉粥"
    ],
    "Name": "面香粥色",
    "Price": 15,
    "Description": null,
    "Address": "新安街道21区灵芝园A座12号",
    "lat": 22.572366254246912,
    "lng": 113.91628166136486,
    "Comments": [
      "感觉口感还是不错的，还有豆干，份量也够大。",
      "还不错这家店，每次都来吃，人还是不错的，比较多，今天的小米粥有点凉，望下次注意保温加热。",
      "早餐中餐今天都在这里了，感觉还不错，北方口味",
      "环境好，服务好，客服人也很好，小米粥味道不错，韭菜盒子与原味饼都是好吃的素食。谢谢。",
      "很好吃的一家店哦，特别是早点葱油饼，油条豆浆韭菜盒子等等。超级喜欢他家的肠粉，汤很棒",
      "来吃早餐的人越来越多，以品质和口味取胜。一家厚道的山东人开的店",
      "试试吧！！第一次来买，还没吃呢。。。",
      "菜品很适合北方人口味，面条很好吃",
      "口味不错，早餐吃的挺好！小米粥，油条豆浆好吃！勤诚达装修找黄工13530991530",
      "面真的很好吃，离公司也近，以后吃面就这家啦！"
    ],
    "CommentCount": 10
  },
  {
    "Item": [
      "酸辣鸡肾面",
      "清汤抄手",
      "清汤排骨面",
      "沫若双打面",
      "牛肉面",
      "肥肠面"
    ],
    "Name": "外婆的面",
    "Price": 15,
    "Description": null,
    "Address": "马蹄山三巷9号",
    "lat": 22.658324287751824,
    "lng": 114.07297803209887,
    "Comments": [
      "对于这家餐馆，更喜欢这个招牌！赞",
      "无骨鸡爪，鸡脚筋，还有海带木耳挺好吃的，想吃辣的…可以来…刚问了晚上十点关门",
      "份量还可以（3两左右），味道不说和重庆当地的老店相比，在坂田这片算非常不错了，服务态度也好",
      "今天特意带朋友过来吃  战斗力还是杠杠滴  看来已经爱上外婆的面了",
      "很好吃m，味道不错！服务态度也挺好！里面的小吃也好吃，我们吃得精光！",
      "挺不错的，冰粉很好吃，面的味道也很好，价格实惠，下次还会来。",
      "特意跑过来吃个东西  味道不错  有时间还会过来",
      "额，一般般...吃了肚子...不太舒服",
      "喜欢外婆、喜欢这面、你可以也试试。",
      "面很好吃，不够吃还可以加面，特别好",
      "好吃，特别是钵钵鸡，也就是冷串串，比较地道。就是贵，比四川贵很多。",
      "位置不错。饭菜也很可口。推荐下次再过来。卫生干净，推荐下次再来。",
      "超级好吃！老顾客啦！！",
      "很好吃，够辣，我来了很多次啦！很入味，吃了还想再吃！！！！",
      "麻辣粉真过瘾！清汤抄手也很适合小孩子，杂酱面也好吃哦！",
      "面条很棒 很有四川的我感觉。算是迟到的比较正宗的了",
      "地地道道地地道道地地道道地地道道地地道道地地道道",
      "辣肠很好吃  很有味道   腐竹也很不错   面汤比较自然  很香",
      "味道很四川，想家的时候吃一碗，也不怎么想了。",
      "这家店东西味道还不错哦，里面也挺安静的，挺好",
      "非常好，味道家乡味，一点没变，好吃常光顾，",
      "好吃，经常来吃，就是我喜欢的味道，很开胃哦",
      "小店不错，干净，还很好吃，味道非常好！！",
      "面好吃，叶儿粑，串串都好吃，图二一般",
      "都是干面，为什么别人有汤我没有",
      "味道不错，价格适中，推荐鸡脚",
      "味道不错！口感很好，好评！",
      "吃了一份酸辣粉，一点嚼劲都没有，没有韧性，一夹就断，酸辣粉跟果冻似得，不好吃。酸辣粉不推荐，其他的没吃过",
      "别的不知道怎么样，清炖土鸡汤面差到爆～，希望能改进",
      "不错，味道非常地道，下次还来，多尝尝其它味道",
      "老板人好！常去吃！主要是太好吃了 停不下来！",
      "呵呵呵呵呵呵呵呵呵呵呵呵呵呵呵很好",
      "家乡的味道，正宗四川味，辣椒就是家里的那种，香辣香辣的，超爽！下次会再来",
      "老板人挺好的，味道也相当不错",
      "有一点点味道，说不出来✔",
      "好多好多次啦！数不清啦！",
      "今天走一站路专门过来吃的",
      "推荐这家的小吃，味道好",
      "夏天吃凉粉还是不错的",
      "没吃过的朋友一定要吃串串，没去过四川的朋友可以尝试凉糕和冰粉",
      "挺不错的，态度也好",
      "味道不正宗  吃的招牌牛肉面 要醋要了很多次 最后吃完了也没看到醋",
      "好吃，味道很正！",
      "还可以，不是很贵",
      "很辣，很够味哦，超爱的超大份，店主也很好，很细心",
      "好地道 好嘛啦 好吃 下次带朋友一起来 好吃的一起来分享",
      "老板人很好，非常亲切，口味也很不错，好评！",
      "很好吃，酸酸辣辣的，环境也很干净，不错",
      "味道很好，就是偏远了些，价格可以更合理",
      "吃出了我奶奶做的味道，全素，却很香，",
      "不错，棒棒哒，下次还会来！！！",
      "很好很好，已经吃了很多次啦！",
      "非常棒，钵钵鸡，红油抄手～～",
      "味道好 老板人也很不错 经常来吃",
      "招牌面肥肠就那么一丢丢啊？",
      "师傅年轻帅气，手艺很好！赞",
      "总体口味不错，尤其是串串",
      "不错，小吃有四川的味道",
      "味道不错，就是价格小贵",
      "串串还不错，其他就还好",
      "味道不错，有重庆的味道",
      "味道很成都很乐山，赞",
      "环境安静怡人，口味符合我喜欢的清淡，排骨汤很入味，服务也好！",
      "还可以    有点小贵  小贵的",
      "还不错咯，环境味道",
      "不错嘛，味道好极了，用我们美国话是very good！！！！",
      "好吃，分量有点儿少",
      "好吃 回头客很多次了",
      "好吃，满意^_^",
      "相当地道的川味！",
      "很好吃，下次还来",
      "超级好！已经来过非常多次了！！！！冷串超级好吃！",
      "服务好，味道非常不错",
      "跟老家比略贵，但是味道很正宗了，以后还回来",
      "一个讨厌吃面的人最喜欢来的面馆",
      "环境很好，味道超棒，大家都可以来试试！以后会经常来",
      "大佛凉面，冲这名字吃的作为一个北方人，没吃出味道，不过还是给好评，都不容易",
      "环境很好，味道不错，以后会经常光顾！",
      "还可以哦(⊙o⊙)哦"
    ],
    "CommentCount": 79
  },
  {
    "Item": [
      "虾干排骨腊肠煲仔饭",
      "酸辣大肠煲仔饭",
      "烧鸭粉面",
      "叉烧排骨煲仔饭",
      "香辣牛肉煲仔饭",
      "梅菜肉饼煲仔饭",
      "咸鱼五花肉煲仔饭",
      "软糯南瓜饼",
      "东莞三腊煲仔饭",
      "咸鱼鸡粒煲仔饭"
    ],
    "Name": "农家庄煲仔饭(松岗二店)",
    "Price": 15,
    "Description": null,
    "Address": "松岗松柏路爱国六街5号(松柏路哥哥乐后面)",
    "lat": 22.773035620714186,
    "lng": 113.85027848437994,
    "Comments": [
      "很好吃，味道不错，个人很喜欢吃葱姜猪肚饭。特别香^_^",
      "环境不错，位置也好找，在哥哥乐后面，口味好，还有炖盅，价格不贵，值得你尝试！",
      "环境可以，服务快。主要是小灶米饭很好吃。每每路过就会进去吃吃。",
      "环境挺好的，服务也好，份量也可以，味道就不用说了，赞",
      "本来想找回当年的味道，制其实区别大那味难寻",
      "第一次到这家店，感觉还可以吧！价钱不贵！",
      "东西不错，价格比快餐稍贵，其他的还行",
      "经常去吃。。很不错",
      "小伙伴们很喜欢吃，",
      "相对来说，可以。",
      "好吃，卫生，环境好",
      "还可以，味道还行",
      "周末闲暇时还可以，因时间要等得长一点，正宗的粤菜口味。",
      "味道可口鲜美，服务态度好，是个好去处。",
      "味道很正，环境卫生服务都不错。"
    ],
    "CommentCount": 15
  },
  {
    "Item": [
      "牛腩汤米粉",
      "咸蛋蒸肉饼饭",
      "牛肉丸汤米粉",
      "猪肉丸汤米粉",
      "肉碎腌面",
      "手撕鸡腌面",
      "牛腩腌面",
      "花生蒸排骨饭",
      "肉碎腌米粉",
      "招牌特色腌面"
    ],
    "Name": "客家三及第(蔡屋围店)",
    "Price": 15,
    "Description": null,
    "Address": "蔡屋围新九坊17楼103号",
    "lat": 22.54571508387491,
    "lng": 114.11457775177725,
    "Comments": [
      "份量十足，味道也过的去，尤其喜欢这家的辣椒，就是空间小，环境有点差，不然还是不错的！",
      "很好很好，炒鸡好！",
      "惦记三及第好久了，今天中午正好路过，来一碗三及第汤面尝尝",
      "很满意，服务态度很好，份量足，口味新鲜，吃着健康",
      "好好好好好好好好好好好好。",
      "感觉味道一般，价格不便宜。",
      "肉质鲜嫩，汤汁美味，份量足，服务超好，每次吃了都还想再来，值得推荐",
      "份量足，老板态度好，好吃",
      "味道好，老板热情",
      "店家服务态度和味道都很好，就是店面有点小",
      "早上来，食材都很新鲜，味道也挺好。",
      "经常来   这家店的菜新鲜  超级喜欢",
      "每次下了班兜过来吃。每次都点不同的。忠实粉丝。重点是服务态度好好。也很好吃的。而且也不算贵。",
      "老板服务超好。以后下班没有胃口的时候可以来吃了。",
      "味道很好，份量很多的一家",
      "五及第汤，用料很足，满满一碗，有猪肉，猪腰，猪肝，猪小肠，猪心，加了少许枸杞叶，用料新鲜，汤很清新。双丸汤，猪肉丸和牛肉丸，很爽口，不错。腌面，面条劲道，入味，挺不错的。"
    ],
    "CommentCount": 16
  },
  {
    "Item": [
      "辣翅",
      "蟹黄汉堡",
      "七虾汉堡",
      "奥尔良鸡肉堡",
      "板烧鸡肉堡",
      "可乐",
      "薯条",
      "麦香鸡肉饼汉堡",
      "翡翠蔬菜汉堡",
      "墨西哥鸡肉卷卷"
    ],
    "Name": "非凡汉堡",
    "Price": 15,
    "Description": null,
    "Address": "弓村八巷8号",
    "lat": 22.666204572719366,
    "lng": 114.03322157693651,
    "Comments": [
      "来了很多次，一次性买了很多，这里环境不错，不拥挤，感觉可乐特别好喝",
      "来了好几次了，这家的汉堡很脆，可乐也很好喝，离家也近很方便啊！",
      "环境设备一流。不错不错，味道也挺好",
      "挺不错的，味道还可以，经常跟同事过来这里吃夜宵，有时候拿来当下午茶，价格也挺实惠的，以后会经常来",
      "每个星期来一次，中毒太深，还好只是在楼下，很方便。",
      "此店服务，味道还不错，下次在来吃",
      "来过很多次了，很喜欢这里的环境和味道，以后有时间还会经常来喔",
      "老顾客老顾客老顾客老顾客老顾客老顾客老顾客",
      "每次去店里，服务很好，不用等太久",
      "还不错，味道挺好",
      "服务员态度超好环境也很干净关键是 WiFi也超好",
      "不错，经常吃，性价比高，味道也很好吃，环境好",
      "很好吃，量足，懒得煮饭，下楼吃汉堡包鸡肉卷",
      "味道不错，以后想吃就来买",
      "还没吃，应该可以吧？",
      "还不错，吃了好几次了。这个价格真的很优惠。推荐",
      "来吃过几次，个人感觉还不错，小朋友也很喜欢。",
      "这家的汉堡不错，就是涨价了一点点，不过也还好",
      "还不错，经常吃，不过大部分都是在美图上点的",
      "口味有点差，，，，，，，，，，，，，，，",
      "口味虽然和麦记和KFC没得比，但是实惠啊",
      "比肯德基麦当劳还贵  味道也比不上",
      "不错，就是这些快餐不能吃太多次",
      "一切的一切，非常好，满分",
      "很好，还可以，味道一般",
      "服务很好，东西也行好吃",
      "还不错吧，就是有点贵",
      "不错，挺好吃，也不贵",
      "俺嗷嗷嗷嗷嗷嗷嗷嗷啊",
      "好好好好好好好好好好好好好好好好好好好好好好好好好好好",
      "很好哦，经常吃，不错哈哈哈哈哈哈哈哈哈哈哈哈哈哈",
      "可乐好喝，汉堡也好吃",
      "不错，挺好吃，也挺实惠。经常和朋友一起过来吃"
    ],
    "CommentCount": 33
  },
  {
    "Item": [
      "萝卜牛腩",
      "牛肉丸粉",
      "面筋牛杂",
      "豆泡牛杂",
      "面筋牛腩",
      "面筋牛肚",
      "面筋牛肉丸",
      "豆腐牛肚",
      "豆泡牛腩",
      "豆泡牛肉丸"
    ],
    "Name": "儒子牛杂",
    "Price": 15,
    "Description": null,
    "Address": "富盈门D1-105商铺",
    "lat": 22.593295176724855,
    "lng": 113.89576202792942,
    "Comments": [
      "不错哈。味道鲜美，之前没去过那里吃，现在吃起来味道还是不错的，下次就直接选择它啦。价格也便宜。吃过才知道哦",
      "非常好吃！连续去多次了！晚上去的时候看到老板好帅！",
      "很地道 汤入味 牛杂也很烂吃起来口感好 值得推荐",
      "这家牛杂的味道非常好，以后一定会常来的！",
      "味道真的可以哦。怎么才能加盟呢",
      "还可以，虽然店很迷你，但是人还是蛮多的，晚上10点以后半价",
      "特别棒特别好吃。料也很足。会经常光顾。",
      "味道特别好，棒棒哒，会经常来光顾的",
      "好吃，就是店面小，一直都有在吃",
      "吃完了，挺不错的。",
      "很好吃，老板很好"
    ],
    "CommentCount": 11
  }
]
